Workbook

Sheet INÍCIO
A1: SPIRIT WALKER · ZOO CHOBER CHABER (rota Mattjestic) — Nível 1 → 100
A2: PoE 2 0.5.5 · Liga Forbidden Rites · atualizado 15/09/2026 · rota barata com trade + opção completa. Edite só as células AMARELAS.
A4: ONDE ESTOU AGORA
A5: Seu nível atual | B5: 35
A6: Modo de investimento | B6: Barato
A7: Spirit total (do jogo) | B7: 191
A9: Fase atual | B9: =INDEX(Listas!$B$2:$B$9,MATCH($B$5,Listas!$A$2:$A$9,1))
A10: Etapa | B10: =INDEX(Listas!$E$2:$E$9,MATCH($B$5,Listas!$A$2:$A$9,1))
A11: Quem carrega o dano | B11: =INDEX(Listas!$C$2:$C$9,MATCH($B$5,Listas!$A$2:$A$9,1))
A12: Objetivo da fase | B12: =INDEX(Listas!$D$2:$D$9,MATCH($B$5,Listas!$A$2:$A$9,1))
A13: Último marco (até seu nível) | B13: =IFERROR("Nv "&INDEX('Nível 1-100'!$K$4:$K$103,$B$5)&" — "&INDEX('Nível 1-100'!$J$4:$J$103,$B$5),"")
A14: Próximo marco | B14: =IFERROR("Nv "&INDEX('Nível 1-100'!$A$4:$A$103,MATCH(1,'Nível 1-100'!$I$4:$I$103,0))&" — "&INDEX('Nível 1-100'!$C$4:$C$103,MATCH(1,'Nível 1-100'!$I$4:$I$103,0)),"Você chegou ao fim!")
A15: Compra recomendada agora | B15: =IF($B$6="Barato",INDEX('Nível 1-100'!$E$4:$E$103,$B$5),INDEX('Nível 1-100'!$F$4:$F$103,$B$5))
A16: Progresso de marcos | B16: =IFERROR(COUNTIF('Nível 1-100'!$G$4:$G$103,"Feito")/100,0)
A17: Quests permanentes feitas | B17: =COUNTIF(Quests!$F$4:$F$32,"Feito")&" de "&COUNTA(Quests!$C$4:$C$32)
A19: ROTA S-TIER — FASES (a linha dourada é a sua fase)
A20: Fase | B20: Níveis | C20: Etapa | D20: Carry | E20: Dano player/zoo | F20: Ascendência | G20: Sai da fase quando…
A21: Ato 1 | B21: 1–15 | C21: Twister (leveling) | D21: Você: Twister + Whirling Slash | E21: 100% / 0% | F21: — | G21: King in the Mists (+30 Spirit) · Candlemass (+20 vida) · Botas com MS · Nível ~16
A22: Ato 2 | B22: 16–30 | C22: 1ª Ascendência | D22: Você: Twister + urso | E22: 85% / 15% | F22: Wild Protector (Trial of the Sekhemas, Ato 2) | G22: 1ª Ascendência: Wild Protector · Medallion (+1 Charm Slot) · Currency guardada para a troca
A23: Ato 3 | B23: 31–45 | C23: A troca: macaco + urso | D23: Mighty Silverfist (+ urso + 1 esqueleto) | E23: 5% / 95% | F23: The Natural Order (Trial of Chaos, Ato 3) | G23: Silverfist capturado · Twister fora da barra · Pain Offering + Skeletal Warrior funcionando · Ignagduk (+30 Spirit)
A24: Ato 4 | B24: 46–55 | C24: 2 companions + chaos | D24: Silverfist (+ aura bots) | E24: 0% / 100% | F24: — | G24: 2 companions (macaco + aura) · Evergrasping Ring ×2 + Withering Presence · Testes de resistência do Ato 4 feitos
A25: Interlúdios | B25: 56–64 | C25: Esqueletos para o Muster | D25: Silverfist + zoo | E25: 0% / 100% | F25: — | G25: 2+ tipos de esqueleto (quantos couberem no Spirit) · Muster no macaco · Lythara (+40 Spirit) · Resists no cap
A26: Início do Atlas | B26: 65–77 | C26: Catha's Balance + mapping | D26: Macaco (Silverfist/Zekoa) + zoo | E26: 0% / 100% | F26: The Catha's Balance (Trial nível 60+) | G26: Catha's Balance · Chober Chaber equipada · T1–T10 sem mortes · Juntar ~1 div para o Effigy
A27: T15+ (Effigy) | B27: 78–89 | C27: Chober + Giant's Blood + Effigy | D27: Zekoa + Azmerian Wolf + zoo | E27: 0% / 100% | F27: Idolatry (Trial nível 75+) | G27: Giant's Blood + Chober + Effigy · Zekoa com Extra Crits/Haste · 3 aura bots (com Sylvan's Effigy) · Forgotten Warden + Spirit Vessel
A28: Arbiter / Min-max | B28: 90–100 | C28: Mind Over Matter + 27 companions | D28: Zoo inteiro | E28: 0% / 100% | F28: — | G28: Arbiter · Uber Arbiter
A30: CORREÇÕES FEITAS NA PLANILHA ANTIGA
A31: ✔ Spirit Planner antigo somava a coluna errada (fórmulas deslocadas) — refeito com cálculo de eficiência.
A32: ✔ Darkness Enthroned estava como capacete — é um CINTO (Fine Belt).
A33: ✔ Trenchtimbre é maça de uma mão, não spear.
A34: ✔ Comparação de arma: com Catha's Balance vale dano por golpe, não pDPS.
A35: ✔ Linhas de nível repetiam o mesmo texto; agora cada nível tem o marco real e a tabela vai até o 100.
A36: ✔ Sylvan's Effigy é Stoic Sceptre (drop em área 78+).
A37: ✔ Guia base mandava tirar Trusted Kinship com o Effigy: o meta (99%) mantém.
A38: ✔ Effigy tratado como luxo: custa ~1 div na Forbidden Rites.
A39: ✔ Uniques do meta adicionados: Forgotten Warden, Chober Chaber, The Vertex, Treefingers, Alpha's Howl etc.
A40: ✔ Rota refeita em cima do guia do Mattjestic com foco na Chober Chaber.
A41: ✔ Ball Lightning/Lightning Warp removidos (nenhuma variante do Mattjestic usa).
A42: ✔ Corrigido: Pain Offering é central; Skeletal Cleric serve de alvo; Withering Presence vale com Evergrasping Ring.

Sheet Listas
A1: Nível inicial | B1: Fase | C1: Carry | D1: Objetivo | E1: Tag | F1: Ascendência | H1: Status | I1: Sim/Não | J1: Modo | K1: Tipo | L1: Unidade
A2: 1 | B2: Ato 1 | C2: Você: Twister + Whirling Slash | D2: Subir rápido com Twister. Nada de minion ainda: o foco é chegar ao Ato 3 com dinheiro e nível para trocar para o macaco + Chober Chaber. | E2: Twister (leveling) | F2: — | H2: Pendente | I2: Sim | J2: Barato | K2: Companion | L2: %
A3: 16 | B3: Ato 2 | C3: Você: Twister + urso | D3: Wild Protector na 1ª Ascendência e juntar gold/currency para a troca do Ato 3 (Chober Chaber, The Vertex, Treefingers, Rattling Sceptre). | E3: 1ª Ascendência | F3: Wild Protector (Trial of the Sekhemas, Ato 2) | H3: Fazendo | I3: Não | J3: Completo | K3: Outro | L3: Flat
A4: 31 | B4: Ato 3 | C4: Mighty Silverfist (+ urso + 1 esqueleto) | D4: Capturar o Mighty Silverfist com The Natural Order e trocar a build inteira para minions no mesmo dia: Twister sai, entram macaco, urso, 1 Skeletal Warrior e Pain Offering. | E4: A troca: macaco + urso | F4: The Natural Order (Trial of Chaos, Ato 3) | H4: Feito
A5: 46 | B5: Ato 4 | C5: Silverfist (+ aura bots) | D5: Macaco + 1 beast de aura (o limite do Trusted Kinship é 2 companions), marks e curse. Entram Evergrasping Ring (aliados ganham dano de chaos) e Withering Presence (inimigos recebem mais chaos): as duas peças se multiplicam. | E5: 2 companions + chaos | F5: —
A6: 56 | B6: Interlúdios | C6: Silverfist + zoo | D6: Depois do Lythara (+40 Spirit), somar TIPOS de esqueleto para o Muster, um por vez e só enquanto couber no Spirit: cada tipo diferente = +7% more dano no macaco, e o 2º esqueleto libera o Danse Macabre. Vulnerability tira Armour. | E6: Esqueletos para o Muster | F6: —
A7: 65 | B7: Início do Atlas | C7: Macaco (Silverfist/Zekoa) + zoo | D7: The Catha's Balance transforma o dano da SUA arma em dano dos companions (60% por golpe). É aqui que a Chober Chaber vira o centro: maça de 2 mãos com dano base altíssimo, +Minion Skills e +50 Spirit. | E7: Catha's Balance + mapping | F7: The Catha's Balance (Trial nível 60+)
A8: 78 | B8: T15+ (Effigy) | C8: Zekoa + Azmerian Wolf + zoo | D8: Giant's Blood na árvore (maça de 2 mãos + sceptre), Sylvan's Effigy (companions ilimitados + Azmerian Wolf), Forgotten Warden (Spirit Vessel grátis). Os esqueletos saem, porque o Rattling Sceptre dá lugar ao Effigy. O Skeletal Cleric vira o alvo do Pain Offering. | E8: Chober + Giant's Blood + Effigy | F8: Idolatry (Trial nível 75+)
A9: 90 | B9: Arbiter / Min-max | C9: Zoo inteiro | D9: Endgame do Mattjestic: Mind Over Matter (dano sai da mana primeiro), Mageblood e até 27 companions. O macaco vira o único DPS 'puro'; os outros são aura bots super defensivos. | E9: Mind Over Matter + 27 companions | F9: —

Sheet Nível 1-100
A1: NÍVEL 1 → 100 — marco por nível
A2: Linhas com marco real em negrito. Marque Status = Feito. A linha do seu nível fica dourada (nível no INÍCIO).
A3: Nível | B3: Fase | C3: Faça agora (marco) | D3: Foco da fase | E3: Barato (trade) | F3: Completo (currency) | G3: Status | H3: Carry | I3: aux
A4: 1 | B4: Ato 1 | C4: Twister + Whirling Slash. Spear rare ou Splinter of Lorrata. | D4: Subir rápido com Twister. Nada de minion ainda: o foco é chegar ao Ato 3 com dinheiro e nível para trocar para o macaco + Chober Chaber. | E4: Rare spear com mais dano que cair | F4: Kit de uniques baratos do Mattjestic: Splinter of Lorrata → Skysliver (spear), Foxshade (body), 2× Blackheart (anéis), Goldrim (capacete), Wanderlust (botas), Meginord's Girdle, Surefooted Sigil | G4: Pendente | H4: Você: Twister + Whirling Slash | I4: =IF(AND(C4<>"—",A4>INÍCIO!$B$5),1,0) | J4: =C4 | K4: =A4
A5: 2 | B5: Ato 1 | C5: — | D5: Movement Speed → Vida, Resistências, Dano da spear | E5: Botas com Movement Speed | F5: Todos custam poucos Exalts no trade e fazem o Ato 1–2 voar | G5: Pendente | H5: Você: Twister + Whirling Slash | I5: =IF(AND(C5<>"—",A5>INÍCIO!$B$5),1,0) | J5: =IF(C5<>"—",C5,J4) | K5: =IF(C5<>"—",A5,K4)
A6: 3 | B6: Ato 1 | C6: — | D6: Movement Speed → Vida, Resistências, Dano da spear | E6: Qualquer escudo/buckler com Evasion | F6: Kit de uniques baratos do Mattjestic: Splinter of Lorrata → Skysliver (spear), Foxshade (body), 2× Blackheart (anéis), Goldrim (capacete), Wanderlust (botas), Meginord's Girdle, Surefooted Sigil | G6: Pendente | H6: Você: Twister + Whirling Slash | I6: =IF(AND(C6<>"—",A6>INÍCIO!$B$5),1,0) | J6: =IF(C6<>"—",C6,J5) | K6: =IF(C6<>"—",A6,K5)
A7: 4 | B7: Ato 1 | C7: Twister liberado. Herald of Ice quando tiver Spirit. | D7: Movement Speed → Vida, Resistências, Dano da spear | E7: Rare spear com mais dano que cair | F7: Todos custam poucos Exalts no trade e fazem o Ato 1–2 voar | G7: Pendente | H7: Você: Twister + Whirling Slash | I7: =IF(AND(C7<>"—",A7>INÍCIO!$B$5),1,0) | J7: =IF(C7<>"—",C7,J6) | K7: =IF(C7<>"—",A7,K6)
A8: 5 | B8: Ato 1 | C8: — | D8: Movement Speed → Vida, Resistências, Dano da spear | E8: Botas com Movement Speed | F8: Kit de uniques baratos do Mattjestic: Splinter of Lorrata → Skysliver (spear), Foxshade (body), 2× Blackheart (anéis), Goldrim (capacete), Wanderlust (botas), Meginord's Girdle, Surefooted Sigil | G8: Pendente | H8: Você: Twister + Whirling Slash | I8: =IF(AND(C8<>"—",A8>INÍCIO!$B$5),1,0) | J8: =IF(C8<>"—",C8,J7) | K8: =IF(C8<>"—",A8,K7)
A9: 6 | B9: Ato 1 | C9: — | D9: Movement Speed → Vida, Resistências, Dano da spear | E9: Qualquer escudo/buckler com Evasion | F9: Todos custam poucos Exalts no trade e fazem o Ato 1–2 voar | G9: Pendente | H9: Você: Twister + Whirling Slash | I9: =IF(AND(C9<>"—",A9>INÍCIO!$B$5),1,0) | J9: =IF(C9<>"—",C9,J8) | K9: =IF(C9<>"—",A9,K8)
A10: 7 | B10: Ato 1 | C10: — | D10: Movement Speed → Vida, Resistências, Dano da spear | E10: Rare spear com mais dano que cair | F10: Kit de uniques baratos do Mattjestic: Splinter of Lorrata → Skysliver (spear), Foxshade (body), 2× Blackheart (anéis), Goldrim (capacete), Wanderlust (botas), Meginord's Girdle, Surefooted Sigil | G10: Pendente | H10: Você: Twister + Whirling Slash | I10: =IF(AND(C10<>"—",A10>INÍCIO!$B$5),1,0) | J10: =IF(C10<>"—",C10,J9) | K10: =IF(C10<>"—",A10,K9)
A11: 8 | B11: Ato 1 | C11: Hunting Grounds: The Crowbell (2 weapon set points). | D11: Movement Speed → Vida, Resistências, Dano da spear | E11: Botas com Movement Speed | F11: Todos custam poucos Exalts no trade e fazem o Ato 1–2 voar | G11: Pendente | H11: Você: Twister + Whirling Slash | I11: =IF(AND(C11<>"—",A11>INÍCIO!$B$5),1,0) | J11: =IF(C11<>"—",C11,J10) | K11: =IF(C11<>"—",A11,K10)
A12: 9 | B12: Ato 1 | C12: — | D12: Movement Speed → Vida, Resistências, Dano da spear | E12: Qualquer escudo/buckler com Evasion | F12: Kit de uniques baratos do Mattjestic: Splinter of Lorrata → Skysliver (spear), Foxshade (body), 2× Blackheart (anéis), Goldrim (capacete), Wanderlust (botas), Meginord's Girdle, Surefooted Sigil | G12: Pendente | H12: Você: Twister + Whirling Slash | I12: =IF(AND(C12<>"—",A12>INÍCIO!$B$5),1,0) | J12: =IF(C12<>"—",C12,J11) | K12: =IF(C12<>"—",A12,K11)
A13: 10 | B13: Ato 1 | C13: Freythorn: King in the Mists (+30 Spirit). | D13: Movement Speed → Vida, Resistências, Dano da spear | E13: Rare spear com mais dano que cair | F13: Todos custam poucos Exalts no trade e fazem o Ato 1–2 voar | G13: Pendente | H13: Você: Twister + Whirling Slash | I13: =IF(AND(C13<>"—",A13>INÍCIO!$B$5),1,0) | J13: =IF(C13<>"—",C13,J12) | K13: =IF(C13<>"—",A13,K12)
A14: 11 | B14: Ato 1 | C14: — | D14: Movement Speed → Vida, Resistências, Dano da spear | E14: Botas com Movement Speed | F14: Kit de uniques baratos do Mattjestic: Splinter of Lorrata → Skysliver (spear), Foxshade (body), 2× Blackheart (anéis), Goldrim (capacete), Wanderlust (botas), Meginord's Girdle, Surefooted Sigil | G14: Pendente | H14: Você: Twister + Whirling Slash | I14: =IF(AND(C14<>"—",A14>INÍCIO!$B$5),1,0) | J14: =IF(C14<>"—",C14,J13) | K14: =IF(C14<>"—",A14,K13)
A15: 12 | B15: Ato 1 | C15: — | D15: Movement Speed → Vida, Resistências, Dano da spear | E15: Qualquer escudo/buckler com Evasion | F15: Todos custam poucos Exalts no trade e fazem o Ato 1–2 voar | G15: Pendente | H15: Você: Twister + Whirling Slash | I15: =IF(AND(C15<>"—",A15>INÍCIO!$B$5),1,0) | J15: =IF(C15<>"—",C15,J14) | K15: =IF(C15<>"—",A15,K14)
A16: 13 | B16: Ato 1 | C16: — | D16: Movement Speed → Vida, Resistências, Dano da spear | E16: Rare spear com mais dano que cair | F16: Kit de uniques baratos do Mattjestic: Splinter of Lorrata → Skysliver (spear), Foxshade (body), 2× Blackheart (anéis), Goldrim (capacete), Wanderlust (botas), Meginord's Girdle, Surefooted Sigil | G16: Pendente | H16: Você: Twister + Whirling Slash | I16: =IF(AND(C16<>"—",A16>INÍCIO!$B$5),1,0) | J16: =IF(C16<>"—",C16,J15) | K16: =IF(C16<>"—",A16,K15)
... A103: 100 | B103: Arbiter / Min-max | C103: Uber Arbiter. | D103: Mana (Mind Over Matter) → +Minion Skills, Spirit, Evasion/Deflection | E103: Setup do T15 + Mind Over Matter (Lavianga's Spirits sustenta) | F103: Runeforged Pariah Mask · Drakeskin Boots · Barbed Bracers (rares/runeforged do Mattjestic) | G103: Pendente | H103: Zoo inteiro | I103: =IF(AND(C103<>"—",A103>INÍCIO!$B$5),1,0) | J103: =IF(C103<>"—",C103,J102) | K103: =IF(C103<>"—",A103,K102)

Sheet Rota por Fase
A1: ROTA POR FASE — o que jogar, comprar e evitar
A2: Cada bloco é uma fase. 'Barato' = começar com pouco no trade; 'Completo' = seguir a build como deve ser.
A4: ATO 1 · Nv 1–15 · Twister (leveling)
A5: Objetivo | B5: Subir rápido com Twister. Nada de minion ainda: o foco é chegar ao Ato 3 com dinheiro e nível para trocar para o macaco + Chober Chaber.
A6: Carry | B6: Você: Twister + Whirling Slash
A7: Ascendência | B7: —
A8: Árvore | B8: Nós de Twister/projétil perto do início da Huntress. É a única fase em que dano de ataque do jogador faz sentido.
A9: Rotação | B9: Whirling Slash até formar o redemoinho → Twister atravessando o redemoinho (fica maior e mais forte) → Parry para bloquear e contra-atacar bosses → Spear Throw para puxar de longe
A10: Evite | B10: Gastar pontos em minion agora · Comprar gear caro para o Twister: ele sai da barra no Ato 3
A11: Sai da fase quando | B11: King in the Mists (+30 Spirit) · Candlemass (+20 vida) · Botas com MS · Nível ~16
A12: Barato (trade) | D12: Completo (currency)
A13: • Rare spear com mais dano que cair | D13: • Kit de uniques baratos do Mattjestic: Splinter of Lorrata → Skysliver (spear), Foxshade (body), 2× Blackheart (anéis), Goldrim (capacete), Wanderlust (botas), Meginord's Girdle, Surefooted Sigil
A14: • Botas com Movement Speed | D14: • Todos custam poucos Exalts no trade e fazem o Ato 1–2 voar
A15: • Qualquer escudo/buckler com Evasion
A16: Prioridade de stats: Movement Speed > Vida > Resistências > Dano da spear
A18: ATO 2 · Nv 16–30 · 1ª Ascendência
A19: Objetivo | B19: Wild Protector na 1ª Ascendência e juntar gold/currency para a troca do Ato 3 (Chober Chaber, The Vertex, Treefingers, Rattling Sceptre).
A20: Carry | B20: Você: Twister + urso
A21: Ascendência | B21: Wild Protector (Trial of the Sekhemas, Ato 2)
A22: Árvore | B22: Ainda Twister, mas já caminhe para o lado de companion da árvore para o respec do Ato 3 ficar barato.
A23: Rotação | B23: Mesma rotação de Twister → O urso segura o aggro dos bosses
A24: Evite | B24: Gastar todo o gold: o respec do Ato 3 é caro
A25: Sai da fase quando | B25: 1ª Ascendência: Wild Protector · Medallion (+1 Charm Slot) · Currency guardada para a troca
A26: Barato (trade) | D26: Completo (currency)
A27: • Rare spear + botas com MS | D27: • Skysliver (spear) · Foxshade · 2× Blackheart · Goldrim · Wanderlust · Surefooted Sigil · Meginord's Girdle
A28: • Meginord's Girdle se faltar Strength | D28: • Comece a guardar para: Chober Chaber (~2 ex), Treefingers (~5 ex), Rattling Sceptre (qualquer), The Vertex versão 'Equipment' (~0,4 div)
A29: Prioridade de stats: Movement Speed > Vida > Resistências > Spirit
A31: ATO 3 · Nv 31–45 · A troca: macaco + urso
A32: Objetivo | B32: Capturar o Mighty Silverfist com The Natural Order e trocar a build inteira para minions no mesmo dia: Twister sai, entram macaco, urso, 1 Skeletal Warrior e Pain Offering.
A33: Carry | B33: Mighty Silverfist (+ urso + 1 esqueleto)
A34: Ascendência | B34: The Natural Order (Trial of Chaos, Ato 3)
A35: Árvore | B35: Árvore do Mattjestic (Ato 3): Trusted Kinship, Bond of the Mamba, Bond of the Cat, Unspoken Bond, e defesa de Evasion (Blur, Catlike Agility, Escape Velocity). Zero nós de ataque.
A36: Rotação | B36: Entre no pack e deixe o macaco e o urso baterem → Unearth no chão: cria Bone Constructs e quebra Armour (Armour Break III) → Pain Offering em cima do boss (espeta um Skeletal Warrior): +velocidade e +dano para todos os minions por 6 s → Raise Shield se o boss for dar um golpe grande
A37: Evite | B37: Matar o Silverfist antes de ter The Natural Order · Manter Twister/Whirling depois da troca · Ball Lightning / Lightning Warp: não fazem nada pelo macaco
A38: Sai da fase quando | B38: Silverfist capturado · Twister fora da barra · Pain Offering + Skeletal Warrior funcionando · Ignagduk (+30 Spirit)
A39: Barato (trade) | D39: Completo (currency)
A40: • Rattling Sceptre (main) + Trenchtimbre (offhand) — exatamente como o Mattjestic | D40: • Chober Chaber + Rattling Sceptre (com Treefingers dando Giant's Blood)
A41: • Midnight Braid (cinto) · Foxshade/Wanderlust/Blackheart mantidos | D41: • The Vertex versão 'Equipment has no Attribute Requirements' para zerar os requisitos triplicados
A42: • Meginord's Girdle se faltar Strength | D42: • Enfolding Dawn (+100 Spirit no body) para caber mais minions
A43: Prioridade de stats: +Minion Skills > Spirit > Movement Speed > Vida > Resistências
A45: ATO 4 · Nv 46–55 · 2 companions + chaos
A46: Objetivo | B46: Macaco + 1 beast de aura (o limite do Trusted Kinship é 2 companions), marks e curse. Entram Evergrasping Ring (aliados ganham dano de chaos) e Withering Presence (inimigos recebem mais chaos): as duas peças se multiplicam.
A47: Carry | B47: Silverfist (+ aura bots)
A48: Ascendência | B48: —
A49: Árvore | B49: Árvore do Mattjestic (Ato 4): Easy Going, Inspiring Ally, Bond of the Wolf somam aos Bonds do Ato 3.
A50: Rotação | B50: Sniper's Mark no boss (com Mark for Death: quebra Armour) → Pain Offering em cima do boss → Unearth para mais corpos/Armour Break → Deixe o zoo bater
A51: Evite | B51: Trocar Evergrasping Ring por rare de resist sem repor o chaos: o Wither perde sentido · Pegar nós de ataque para você
A52: Sai da fase quando | B52: 2 companions (macaco + aura) · Evergrasping Ring ×2 + Withering Presence · Testes de resistência do Ato 4 feitos
A53: Barato (trade) | D53: Completo (currency)
A54: • Rattling Sceptre + Trenchtimbre | D54: • Chober Chaber + Rattling Sceptre + Treefingers + The Vertex
A55: • Evergrasping Ring ×2 (aliados ganham 15–25% do dano como chaos) | D55: • Evergrasping Ring ×2 · Enfolding Dawn · Bushwhack
A56: • Enfolding Dawn (+100 Spirit) · Bushwhack (botas) · Midnight Braid | D56: • Primeiro Quill/Coconut Crab com Haste Aura
A57: • Charms contra bleed/ignite
A58: Prioridade de stats: +Minion Skills > Spirit > Vida > Resistências > Movement Speed
A60: INTERLÚDIOS · Nv 56–64 · Esqueletos para o Muster
A61: Objetivo | B61: Depois do Lythara (+40 Spirit), somar TIPOS de esqueleto para o Muster, um por vez e só enquanto couber no Spirit: cada tipo diferente = +7% more dano no macaco, e o 2º esqueleto libera o Danse Macabre. Vulnerability tira Armour.
A62: Carry | B62: Silverfist + zoo
A63: Ascendência | B63: —
A64: Árvore | B64: Árvore do Mattjestic (Ato 5): adiciona Bond of the Owl.
A65: Rotação | B65: Vulnerability no pack/boss → Pain Offering → Deixe o zoo bater
A66: Evite | B66: Colocar supports de dano nos esqueletos: eles existem para o Muster e para o Pain Offering · Entrar no Atlas com resists abaixo de 75%
A67: Sai da fase quando | B67: 2+ tipos de esqueleto (quantos couberem no Spirit) · Muster no macaco · Lythara (+40 Spirit) · Resists no cap
A68: Barato (trade) | D68: Completo (currency)
A69: • Trenchtimbre na main-hand + Rattling Sceptre no offhand | D69: • Chober Chaber + Rattling Sceptre + Treefingers + The Vertex
A70: • Enfolding Dawn · Bushwhack · Evergrasping Ring ×2 · Meginord's Girdle | D70: • Enfolding Dawn · Bushwhack · Evergrasping Ring ×2
A71: • Capacete Runeforged (Elite Greathelm) para Runic Ward | D71: • Ventor's Gamble se sobrar dinheiro
A72: Prioridade de stats: +Minion Skills > Spirit > Vida > Resistências (cap 75%) > Movement Speed
A74: INÍCIO DO ATLAS · Nv 65–77 · Catha's Balance + mapping
A75: Objetivo | B75: The Catha's Balance transforma o dano da SUA arma em dano dos companions (60% por golpe). É aqui que a Chober Chaber vira o centro: maça de 2 mãos com dano base altíssimo, +Minion Skills e +50 Spirit.
A76: Carry | B76: Macaco (Silverfist/Zekoa) + zoo
A77: Ascendência | B77: The Catha's Balance (Trial nível 60+)
A78: Árvore | B78: Árvore do Mattjestic (Mapping T1-10): Sturdy Ally, Captivating Companionship, Sic 'Em, The Howling Primate, The Fabled Stag, Enhanced Reflexes.
A79: Rotação | B79: Despair no pack (tira resistência a chaos) → Sniper's Mark no boss → Pain Offering → Refutation antes de um golpe grande (gasta Runic Ward e bloqueia tudo)
A80: Evite | B80: Julgar a arma pelo DPS: com Catha vale o dano por golpe (a Chober Chaber bate devagar e é a melhor) · Tirar os esqueletos antes do Effigy
A81: Sai da fase quando | B81: Catha's Balance · Chober Chaber equipada · T1–T10 sem mortes · Juntar ~1 div para o Effigy
A82: Barato (trade) | D82: Completo (currency)
A83: • Trenchtimbre + Rattling Sceptre até juntar para a Chober Chaber | D83: • Chober Chaber (Runeforged) + Rattling Sceptre + Treefingers + The Vertex
A84: • Evergrasping Ring ×2 · armaduras Runeforged (Runic Ward para o Refutation) | D84: • Sylvan's Effigy assim que tiver ~1 div (substitui o Rattling Sceptre)
A85: • Jewels: From Nothing · Undying Hate | D85: • From Nothing · Undying Hate
A86: Prioridade de stats: Dano base da main-hand (Catha) > +Minion Skills > Spirit > Vida > Resistências > Runic Ward
A88: T15+ (EFFIGY) · Nv 78–89 · Chober + Giant's Blood + Effigy
A89: Objetivo | B89: Giant's Blood na árvore (maça de 2 mãos + sceptre), Sylvan's Effigy (companions ilimitados + Azmerian Wolf), Forgotten Warden (Spirit Vessel grátis). Os esqueletos saem, porque o Rattling Sceptre dá lugar ao Effigy. O Skeletal Cleric vira o alvo do Pain Offering.
A90: Carry | B90: Zekoa + Azmerian Wolf + zoo
A91: Ascendência | B91: Idolatry (Trial nível 75+)
A92: Árvore | B92: Árvore do Mattjestic (Giant's Blood Endgame): Giant's Blood, Polymathy (atributos), Enduring/Avoiding Deflection, Long Distance Relationship, The Winter Owl.
A93: Rotação | B93: Mace Strike (Einhar's Beastrite) finalizando raros: rouba 2 modificadores por 300 s → Voltaic Mark no boss → Pain Offering (Brutus' Brain: o espinho não morre) → Refutation antes do golpe grande → O resto é automático
A94: Evite | B94: Tirar Trusted Kinship · Pegar Idolatry enquanto depende de runas de resistência
A95: Sai da fase quando | B95: Giant's Blood + Chober + Effigy · Zekoa com Extra Crits/Haste · 3 aura bots (com Sylvan's Effigy) · Forgotten Warden + Spirit Vessel
A96: Barato (trade) | D96: Completo (currency)
A97: • Chober Chaber + Sylvan's Effigy | D97: • Mesmo set + Idolatry com Idols em tudo
A98: • Forgotten Warden · Lavianga's Spirits | D98: • Prism of Belief +2/+3 Tamed Companion
A99: • Spiteful Floret no weapon set 2 (Sanguine Revelry) | D99: • Morior Invictus se preferir tank
A100: • Jewels: Controlled Metamorphosis · Megalomaniac · From Nothing
A101: Prioridade de stats: Dano base da Chober Chaber > +Minion Skills > Spirit > Evasion/Deflection > Resistências > Atributos (Giant's Blood triplica requisitos)
A103: ARBITER / MIN-MAX · Nv 90–100 · Mind Over Matter + 27 companions
A104: Objetivo | B104: Endgame do Mattjestic: Mind Over Matter (dano sai da mana primeiro), Mageblood e até 27 companions. O macaco vira o único DPS 'puro'; os outros são aura bots super defensivos.
A105: Carry | B105: Zoo inteiro
A106: Ascendência | B106: —
A107: Árvore | B107: Árvore do Mattjestic (Endgame Mapping): Mind Over Matter, The Soul Meridian, Beastial Skin, The Wild Cat, Lifelong Friend.
A108: Rotação | B108: Mace Strike finalizando raros → Voltaic Mark → Refutation → Deixe o zoo
...

Sheet Skills & Supports
A1: SKILLS & SUPPORTS — rota Chober Chaber (Mattjestic)
A2: Filtre a coluna Fase. Coluna J explica cada skill; no fim da aba, o que cada support faz.
A3: Fase | B3: Skill | C3: Set | D3: Support 1 | E3: Support 2 | F3: Support 3 | G3: Support 4 | H3: Support 5 | I3: Função | J3: Por que está na build
A4: Ato 1 | B4: Twister | C4: — | D4: Retreat III | E4: Elemental Armament III | F4: Projectile Acceleration I | I4: Dano principal | J4: Twister é a skill de leveling mais rápida da Huntress: redemoinhos que atravessam packs inteiros.
A5: Ato 1 | B5: Whirling Slash | C5: — | D5: Rapid Attacks I | E5: Rage II | I5: Cria o redemoinho | J5: Cada Whirling Slash cria/aumenta um redemoinho; o Twister disparado por dentro dele ganha dano e tamanho.
A6: Ato 1 | B6: Herald of Ice | C6: — | D6: Cold Attunement | E6: Concentrated Area | I6: Clear extra | J6: Inimigos congelados explodem e limpam o resto do pack sem apertar nada.
A7: Ato 1 | B7: Parry | C7: — | I7: Defesa ativa | J7: Bloqueia o próximo golpe e deixa o inimigo vulnerável: salva de bosses do Ato 1–2.
A8: Ato 1 | B8: Spear Throw | C8: — | I8: Puxar de longe | J8: Vem da própria spear; útil para puxar packs.
A9: Ato 2 | B9: Wild Protector | C9: Asc. | D9: Magnified Area I | E9: Rage II | I9: Tank + dano extra | J9: O urso não conta no limite de companions: é um minion grátis que segura bosses e dá Intimidate.
A10: Ato 2 | B10: Twister | C10: — | D10: Retreat III | E10: Elemental Armament III | F10: Projectile Acceleration I | I10: Dano principal | J10: Continua sendo o dano até capturar o macaco.
A11: Ato 2 | B11: Whirling Slash | C11: — | D11: Rapid Attacks I | E11: Bleed I | I11: Redemoinho | J11: Bleed no Whirling ajuda nos bosses.
A12: Ato 2 | B12: Parry | C12: — | I12: Defesa ativa | J12: Continua útil até o Ato 3.
A13: Ato 2 | B13: Spear Throw | C13: — | I13: Puxar de longe | J13: Vem da spear.
A14: Ato 3 | B14: Tame Beast (Mighty Silverfist) | C14: — | D14: Feeding Frenzy II | E14: Rage II | F14: Rapid Attacks I | G14: Heft | I14: CARRY | J14: O macaco é o dano da build inteira: bate físico em área, muito rápido, com 25% de chance de crítico base. Tudo abaixo existe para deixá-lo mais forte ou mais vivo.
A15: Ato 3 | B15: Wild Protector | C15: Asc. | D15: Magnified Area I | I15: Tank | J15: Segura o aggro e conta como mais um TIPO de minion para o Muster.
A16: Ato 3 | B16: Skeletal Warrior (1 esqueleto) | C16: — | D16: Sacrificial Lamb I | E16: Meat Shield I | I16: Combustível do Pain Offering | J16: Vem como gem do Rattling Sceptre. Você só precisa de UM esqueleto vivo: ele é o alvo que o Pain Offering espeta. Não é para dar dano. Sacrificial Lamb garante que o espinho pegue ele (e nunca o macaco) e Meat Shield mantém ele vivo.
A17: Ato 3 | B17: Pain Offering | C17: — | D17: Prolonged Duration II | E17: Sacrificial Offering | I17: Buff de dano dos minions | J17: Espeta 1 esqueleto: minions a até 6 m ganham até +29% attack speed e +58% dano. Não reserva Spirit, só gasta mana. Danse Macabre só entra quando você tiver 2 esqueletos vivos (Interlúdios em diante); com 1 esqueleto ele não funciona.
A18: Ato 3 | B18: Unearth | C18: — | D18: Armour Break III | I18: Quebra de Armour + corpos | J18: Spell sua que cria Bone Constructs dos corpos e, com Armour Break III, tira Armour do inimigo: o macaco passa a bater o dano físico inteiro.
A19: Ato 3 | B19: Raise Shield | C19: — | I19: Defesa ativa | J19: Só funciona com escudo ou buckler equipado. Com sceptre + maça (o set desta rota) ele não pode ser usado: deixe fora da barra se não tiver escudo.
A20: Ato 3 | B20: Tame Beast (2º beast: aura) | C20: — | D20: Last Gasp | E20: Loyalty | I20: Aura bot | J20: Entra quando o Spirit deixar (depois do Ignagduk, +30 Spirit, no nível ~40). Escolha pelo modificador de aura (Haste/Physical), não pelo dano. Last Gasp mantém a aura viva, Loyalty faz ele tomar parte do seu dano.
A21: Ato 3 | B21: Tame Beast (vazia) | C21: — | I21: Captura | J21: Deixe uma gem de Tame Beast livre para capturar o próximo beast com mod bom.
A22: Ato 3 | B22: Twister | C22: — | D22: Retreat III | E22: Elemental Armament III | I22: Só até capturar | J22: Tire da barra no respec.
A23: Ato 3 | B23: Whirling Slash | C23: — | D23: Rapid Attacks I | E23: Bleed I | I23: Só até capturar | J23: Tire da barra no respec.
A24: Ato 4 | B24: Tame Beast (Mighty Silverfist) | C24: — | D24: Feeding Frenzy II | E24: Rage II | F24: Rapid Attacks II | G24: Heft | I24: CARRY | J24: Rapid Attacks sobe para II: mais golpes por segundo.
A25: Ato 4 | B25: Wild Protector | C25: Asc. | D25: Magnified Area I | E25: Armour Break III | I25: Tank + Armour Break | J25: O urso também passa a quebrar Armour, somando com o Unearth.
A26: Ato 4 | B26: Skeletal Warrior (ou 1 Arsonist) | C26: — | D26: Sacrificial Lamb I | E26: Amanamu's Tithe | I26: Combustível | J26: Só UM esqueleto: ele é o alvo do Pain Offering. Pode ser o Skeletal Warrior do Rattling Sceptre OU um Skeletal Arsonist — se você já usa o Arsonist, NÃO ative o Warrior também, porque os dois não cabem no Spirit do Ato 4. Sacrificial Lamb I garante que o Pain Offering espete esse esqueleto.
A27: Ato 4 | B27: Pain Offering | C27: — | D27: Prolonged Duration II | E27: Sacrificial Offering | I27: Buff de dano | J27: Continua sendo o botão de boss e não reserva Spirit. Com 1 esqueleto use Prolonged Duration II + Sacrificial Offering; Danse Macabre só quando tiver 2 esqueletos vivos.
A28: Ato 4 | B28: Withering Presence | C28: — | I28: Wither em área | J28: Inimigos na sua Presence recebem Wither (mais dano de chaos). Sozinha seria fraca, mas com Evergrasping Ring o zoo inteiro bate chaos extra.
A29: Ato 4 | B29: Sniper's Mark | C29: — | D29: Mark for Death | E29: Prolonged Duration II | I29: Marca o boss | J29: Mark for Death faz os hits no alvo marcado quebrarem Armour.
A30: Ato 4 | B30: Unearth | C30: — | D30: Prolonged Duration I | I30: Corpos + controle | J30: Bone Constructs duram mais.
A31: Ato 4 | B31: Tame Beast (2º beast: aura Haste) | C31: — | D31: Loyalty | E31: Last Gasp | I31: Aura bot | J31: O beast de aura vem logo depois do macaco: a aura de Haste acelera o zoo inteiro. Loyalty faz ele absorver parte do seu dano e Last Gasp mantém a aura ativa mesmo depois de morrer.
A32: Ato 4 | B32: Tame Beast (3º beast: só com Sylvan's Effigy) | C32: — | I32: Captura / guardar para o Effigy | J32: Com Trusted Kinship o limite é 2 companions de tipos diferentes (texto do keystone). O 3º só pode ficar ativo com o Sylvan's Effigy ("any number of Companions"). Até lá, use esta gem vazia só para capturar e guardar um Swarming Wisp / Plague Swarm com aura Physical.
A33: Ato 4 | B33: Raise Shield | C33: — | I33: Defesa ativa | J33: Só funciona com escudo ou buckler equipado. Com sceptre + maça (o set desta rota) ele não pode ser usado: deixe fora da barra se não tiver escudo.
A34: Ato 4 | B34: Skeletal Warrior (2º esqueleto) | C34: — | D34: Sacrificial Lamb I | I34: Só se sobrar Spirit | J34: Um 2º esqueleto libera o Danse Macabre no Pain Offering (+30% efeito). Com ~210 Spirit no nível 49 ele NÃO cabe junto com Silverfist + aura + Withering Presence + 1 esqueleto. Deixe para os Interlúdios.
A35: Interlúdios | B35: Tame Beast (Mighty Silverfist) | C35: — | D35: Feeding Frenzy II | E35: Rage II | F35: Rapid Attacks II | G35: Heft | H35: Muster | I35: CARRY | J35: Entra o 5º support: Muster. Com urso + macaco + aura bots + 5 tipos de esqueleto, são ~9 tipos → ~+63% more dano.
A36: Interlúdios | B36: Wild Protector | C36: Asc. | D36: Magnified Area I | E36: Armour Break III | F36: Minion Splash II | I36: Tank + área | J36: Minion Splash: o urso acerta o pack todo.
A37: Interlúdios | B37: Skeletal Warrior | C37: — | D37: Sacrificial Lamb II | E37: Amanamu's Tithe | I37: Combustível | J37: O esqueleto alvo do Pain Offering (Sacrificial Lamb II alcança 6 m). Se você usa Arsonist como esqueleto principal, ele ocupa esta vaga.
A38: Interlúdios | B38: Skeletal Frost Mage | C38: — | I38: Tipo extra (Muster) · opcional | J38: Cada TIPO diferente de minion dá +7% more dano ao macaco com Muster e o 2º esqueleto libera o Danse Macabre. Ative um por vez e só enquanto couber no Spirit: se o painel de skills mostrar Spirit negativo, desligue o último que entrou.
A39: Interlúdios | B39: Skeletal Arsonist | C39: — | I39: Tipo extra (Muster) · opcional | J39: Cada TIPO diferente de minion dá +7% more dano ao macaco com Muster e o 2º esqueleto libera o Danse Macabre. Ative um por vez e só enquanto couber no Spirit: se o painel de skills mostrar Spirit negativo, desligue o último que entrou.
A40: Interlúdios | B40: Skeletal Sniper | C40: — | I40: Tipo extra (Muster) · opcional | J40: Cada TIPO diferente de minion dá +7% more dano ao macaco com Muster e o 2º esqueleto libera o Danse Macabre. Ative um por vez e só enquanto couber no Spirit: se o painel de skills mostrar Spirit negativo, desligue o último que entrou.
A41: Interlúdios | B41: Skeletal Reaver | C41: — | I41: Tipo extra (Muster) · opcional | J41: Cada TIPO diferente de minion dá +7% more dano ao macaco com Muster e o 2º esqueleto libera o Danse Macabre. Ative um por vez e só enquanto couber no Spirit: se o painel de skills mostrar Spirit negativo, desligue o último que entrou.
A42: Interlúdios | B42: Vulnerability | C42: — | D42: Prolonged Duration II | E42: Heightened Curse | I42: Curse | J42: Inimigos amaldiçoados ignoram parte da Armour: o macaco (físico) bate cheio.
A43: Interlúdios | B43: Pain Offering | C43: — | D43: Danse Macabre | E43: Prolonged Duration II | I43: Buff de dano | J43: Com 2 esqueletos vivos (o Warrior + um tipo extra), o Danse Macabre funciona: +30% no buff. Com só 1 esqueleto, troque Danse Macabre por Sacrificial Offering.
A44: Interlúdios | B44: Withering Presence | C44: — | I44: Wither | J44: Continua com Evergrasping Ring.
A45: Interlúdios | B45: Tame Beast (2º beast: aura) | C45: — | D45: Loyalty | E45: Last Gasp | I45: Aura bot | J45: Aura.
A46: Início do Atlas | B46: Tame Beast (Mighty Silverfist → Zekoa) | C46: — | D46: Feeding Frenzy II | E46: Rage III | F46: Rapid Attacks II | G46: Heft | H46: Muster | I46: CARRY | J46: Com a Catha, cada golpe do macaco ganha 60% do dano da Chober Chaber. Rage III e Rapid Attacks II = mais golpes; Heft = golpes maiores.
A47: Início do Atlas | B47: Wild Protector | C47: Asc. | D47: Magnified Area I | E47: Armour Break III | F47: Minion Splash II | G47: Minion Mastery | I47: Tank + Armour Break | J47: Também recebe a Catha's Balance.
A48: Início do Atlas | B48: Skeletal Warrior | C48: — | D48: Amanamu's Tithe | E48: Sacrificial Lamb II | F48: Meat Shield I | I48: Combustível | J48: Continua vindo do Rattling Sceptre.
A49: Início do Atlas | B49: Pain Offering | C49: — | D49: Danse Macabre | E49: Prolonged Duration II | F49: Sacrificial Offering | I49: Buff de dano | J49: Sacrificial Offering: sacrifica 15% da sua vida por +30% efeito e 30% more dano.
A50: Início do Atlas | B50: Skeletal Sniper | C50: — | I50: Tipo extra (Muster) · opcional | J50: Tipo de minion para o Muster.
A51: Início do Atlas | B51: Skeletal Reaver | C51: — | I51: Tipo extra (Muster) · opcional | J51: Tipo de minion para o Muster.
A52: Início do Atlas | B52: Skeletal Cleric | C52: — | I52: Cura + revive esqueletos | J52: Revive os esqueletos que o Pain Offering consome e cura o zoo. Também é esqueleto: serve de alvo do Pain Offering.
A53: Início do Atlas | B53: Despair | C53: — | D53: Prolonged Duration II | E53: Heightened Curse | F53: Rapid Casting I | I53: Curse de chaos | J53: Tira até 49% de resistência a chaos: o chaos do Evergrasping Ring bate muito mais.
A54: Início do Atlas | B54: Tame Beast (2º beast: aura) | C54: — | D54: Last Gasp | E54: Magnified Area I | F54: Meat Shield I | I54: Aura bot | J54: Meat Shield: ele só precisa sobreviver com a aura.
A55: Início do Atlas | B55: Sniper's Mark | C55: — | D55: Mark for Death | I55: Marca | J55: Quebra Armour do alvo.
A56: Início do Atlas | B56: Refutation | C56: — | D56: Prolonged Duration II | E56: Cooldown Recovery II | F56: Efficiency II | G56: Rapid Casting II | I56: Defesa ativa | J56: Gasta todo o seu Runic Ward para bloquear TODOS os hits por um tempo. Runic Ward vem de itens Runeforged/Runemastered — por isso o Mattjestic usa armaduras Runeforged.
A57: T15+ (Effigy) | B57: Tame Beast (Zekoa, the Headcrusher) | C57: — | D57: Feeding Frenzy II | E57: Rage III | F57: Muster | G57: Heft | H57: Rapid Attacks II | I57: CARRY | J57: A versão de Atlas do Silverfist (mapas Riverside/Rupture) pode ter mais modificadores.
A58: T15+ (Effigy) | B58: Azmerian Wolf | C58: Effigy | D58: Feeding Frenzy II | E58: Rapid Attacks II | F58: Rage III | G58: Hulking Minions | H58: Loyalty | I58: 2º dano | J58: Vem do Sylvan's Effigy. Hulking Minions deixa o lobo Gigantic (mais vida e dano).
A59: T15+ (Effigy) | B59: Wild Protector | C59: Asc. | D59: Hulking Minions | E59: Feeding Frenzy II | F59: Muster | G59: Romira's Requital | H59: Catha's Brilliance | I59: Tank + sustain | J59: Romira's Requital: o urso toma 10% do seu dano e você recupera 200% disso como vida. Catha's Brilliance: blind + ignite em volta dele.
A60: T15+ (Effigy) | B60: Spirit Vessel | C60: — | D60: Loyalty | E60: Furious Slam | F60: Arctic Howl | G60: Rapid Attacks II | H60: Rage III | I60: Companion grátis | J60: Vem do Forgotten Warden. Furious Slam (Bear) e Arctic Howl (Werewolf) socketados: +20% more dano por skill diferente.
A61: T15+ (Effigy) | B61: Wolf Pack | C61: — | D61: Rapid Attacks II | E61: Feeding Frenzy II | F61: Loyalty | G61: Rage III | H61: Withering Touch | I61: Corpos + Wither | J61: Vários lobos contam como um companion. Withering Touch aplica Wither para o chaos.
A62: T15+ (Effigy) | B62: Pain Offering | C62: — | D62: Danse Macabre | E62: Prolonged Duration II | F62: Sacrificial Offering | G62: Brutus' Brain | I62: Buff de dano | J62: Brutus' Brain: o espinho não pode ser destruído, então o buff nunca cai. Danse Macabre só funciona com 2 esqueletos vivos: se você tiver só 1 Skeletal Cleric vivo, tire o Danse Macabre (os outros supports continuam valendo).
A63: T15+ (Effigy) | B63: Skeletal Cleric | C63: — | D63: Sacrificial Lamb II | E63: Tecrod's Revenge | F63: Meat Shield II | G63: Elemental Army | I63: Alvo do Pain Offering | J63: Sem Rattling Sceptre, o Cleric é o esqueleto espetado (Sacrificial Lamb II). Tecrod's Revenge mantém ele lutando 20 s depois de morrer.
A64: T15+ (Effigy) | B64: Voltaic Mark | C64: — | D64: Cooldown Recovery II | E64: Eternal Mark | F64: Mark for Death II | G64: Prolonged Duration II | I64: Marca o boss | J64: Eternal Mark: não é consumida na primeira ativação. Mark for Death II: quebra Armour.
A65: T15+ (Effigy) | B65: Mace Strike | C65: — | D65: Einhar's Beastrite | E65: Culling Strike II | F65: Rage III | G65: Rapid Attacks II | H65: Magnified Area II | I65: Rouba modificadores | J65: Vem da Chober Chaber. Não é dano: só finaliza inimigos com vida baixa, e cada raro finalizado te dá 2 modificadores dele (Haste, Extra Damage…) por 5 minutos.
A66: T15+ (Effigy) | B66: Tame Beast (auras ×3) | C66: — | D66: Loyalty | E66: Rage III | F66: Muster | G66: Feeding Frenzy II | H66: Rapid Attacks II | I66: Aura bots | J66: 3 beasts de aura (Haste/Physical/ES/Invulnerability). No Tier-list do Mattjestic: Quill/Coconut Crab (24,9%), Swarming Wisp (21%), Crag Leaper (23,1%).
A67: T15+ (Effigy) | B67: Discipline | C67: Effigy | I67: Aura de ES | J67: Vem do Effigy.
A68: T15+ (Effigy) | B68: Sanguine Revelry | C68: — | I68: Rage + vida | J68: Vem do Spiteful Floret no weapon set 2: Remnants de inimigos com bleed dão Rage e vida.
A69: T15+ (Effigy) | B69: Refutation | C69: — | D69: Prolonged Duration II | E69: Cooldown Recovery II | F69: Efficiency II | G69: Rapid Casting II | H69: Mobility | I69: Defesa ativa | J69: Mobility: pode andar enquanto o buff está ativo.
A70: Arbiter / Min-max | B70: Tame Beast (Zekoa, the Headcrusher) | C70: — | D70: Rage III | E70: Muster | F70: Heft | G70: Feeding Frenzy II | H70: Rapid Attacks II | I70: CARRY (bossing) | J70: Setup de boss. Para mapear, troque Heft/Feeding Frenzy/Rapid Attacks por Minion Splash II + Infernal Legion I + Tecrod's Revenge (dano em área).
A71: Arbiter / Min-max | B71: Azmerian Wolf | C71: Effigy | D71: Loyalty | E71: Rage III | F71: Muster | G71: Feeding Frenzy II | H71: Rapid Attacks II | I71: 2º dano | J71: Loyalty no lugar de Hulking Minions: menos Spirit.
A72: Arbiter / Min-max | B72: Wild Protector | C72: Asc. | D72: Romira's Requital | E72: Rage III | F72: Muster | G72: Rapid Attacks II | H72: Catha's Brilliance | I72: Tank + sustain | J72: Romira's Requital continua sendo a maior fonte de vida.
A73: Arbiter / Min-max | B73: Spirit Vessel | C73: — | D73: Loyalty | E73: Devour | F73: Oil Barrage | G73: Salvo | H73: Living Lightning II | I73: Companion grátis | J73: 4 skills diferentes socketadas = +80% more dano do Vessel.
A74: Arbiter / Min-max | B74: Wolf Pack | C74: — | D74: Loyalty | E74: Elemental Army | F74: Infernal Legion I | G74: Withering Touch | H74: Amanamu's Tithe | I74: Corpos + Wither + buffs | J74: Amanamu's Tithe: lobos morrendo te dão modificadores Abyssal.
A75: Arbiter / Min-max | B75: Tame Beast (auras ×5) | C75: — | D75: Loyalty | E75: Last Gasp | F75: Elemental Army | G75: Meat Shield II | H75: Minion Mastery | I75: Aura bots | J75: Setup 100% defensivo: só precisam manter a aura viva.
A76: Arbiter / Min-max | B76: Voltaic Mark | C76: — | D76: Cooldown Recovery II | E76: Prolonged Duration II | F76: Mark for Death II | G76: Eternal Mark | I76: Marca | J76: Igual ao T15.
A77: Arbiter / Min-max | B77: Mace Strike | C77: — | D77: Einhar's Beastrite | E77: Culling Strike II | F77: Rage III | G77: Rapid Attacks III | H77: Magnified Area II | I77: Rouba modificadores | J77: Igual ao T15.
A78: Arbiter / Min-max | B78: Discipline | C78: Effigy | D78: Upwelling II | I78: Aura de ES | J78: Vem do Effigy.
A79: Arbiter / Min-max | B79: Sanguine Revelry | C79: — | I79: Rage + vida | J79: Vem do Spiteful Floret.
A80: Arbiter / Min-max | B80: Refutation | C80: — | D80: Prolonged Duration II | E80: Cooldown Recovery II | F80: Efficiency II | G80: Rapid Casting II | H80: Mobility | I80: Defesa ativa | J80: Igual ao T15.
A82: O QUE CADA SUPPORT FAZ E POR QUE USAR
B83: Amanamu's Tithe | C83: Quando um minion deste skill morre, 50% de chance de VOCÊ ganhar um modificador Abyssal por 20 s (até 3). Esqueletos morrem o tempo todo → buffs grátis.
B84: Arctic Howl | C84: Skill de Werewolf socketada no Spirit Vessel: congela e dá dano de frio aos aliados.
B85: Armour Break I | C85: Quebra de Armour inicial.
B86: Armour Break III | C86: Os golpes quebram Armour dos inimigos. Inimigo sem Armour recebe o dano físico inteiro do macaco.
B87: Bleed I | C87: Chance de Bleed no Whirling Slash (leveling).
B88: Brutality I | C88: Mais dano físico (leveling).
B89: Brutus' Brain | C89: O minion não recebe nem causa dano. No Pain Offering: o espinho não pode ser destruído, então o buff nunca cai no meio do boss.
B90: Catha's Brilliance | C90: Inimigos perto do urso ficam Blind (erram mais) e pegam Ignite baseado na vida do urso.
B91: Clarity I | C91: Regeneração de mana.
B92: Cold Attunement | C92: Herald of Ice com mais dano de frio (leveling).
B93: Concentrated Area | C93: Área menor, dano maior (leveling).
B94: Cooldown Recovery II | C94: Recarga mais rápida (mark/Refutation disponível mais vezes).
... B156: Withering Touch | C156: Chance de aplicar Wither (inimigo recebe mais dano de chaos). Combina com Evergrasping Ring e Uul-Netol's Embrace, que dão dano de chaos.

Sheet Gear
A1: GEAR — do barato ao completo
A2: Barato = poucos Exalts no trade · Valor = bom custo-benefício · Completo = build como deve ser. Preços variam: use as faixas.
A3: Slot | B3: Barato | C3: Valor | D3: Completo | E3: Prioridade de affix | F3: Nota
A4: Main-hand | B4: Atos 1–2: spear rare (Twister). Ato 3: Rattling Sceptre (main) + Trenchtimbre. Início do Atlas: Chober Chaber Runeforged (~0,04 div). | C4: Chober Chaber Runeforged + Treefingers + The Vertex | D4: Chober Chaber Runeforged + Giant's Blood (Treefingers/keystone) + The Vertex | E4: Dano por golpe (min–max) > +Strength > qualquer coisa | F4: Catha's Balance: companions ganham 60% do dano da main-hand. 32% dos zoos com Effigy usam maça de 2 mãos + sceptre.
A5: Offhand | B5: Atos 1–2: qualquer offhand. Ato 3+: Rattling Sceptre (base rare, traz Skeletal Warrior) com +Minion Skills | C5: Sylvan's Effigy (~0,95 div) com Primate Idol + Rabbit Idol | D5: Sylvan's Effigy com Primate + Rabbit Idol | E5: Spirit > +Minion Skills > buffs de companion | F5: Com ~1 div o Effigy entra logo no início do Atlas.
A6: Capacete | B6: Vida + resists + Evasion | C6: +1/+2 Minion Skills com Idol of Ralakesh, ou Alpha's Howl (+100 Spirit) se faltar reserva | D6: +2 Minion Skills com Idol of Ralakesh, ou The Vertex para a Chober Chaber | E6: Minion Skills; vida; resist; Evasion→Deflection | F6: Starkonja's Head é defesa barata na campanha.
A7: Body Armour | B7: Evasion + vida + resists | C7: Forgotten Warden (~0,21 div) com Fox Idol | D7: Forgotten Warden Runemastered ou Morior Invictus (~6 div) | E7: Evasion; Deflection; vida; resist | F7: Forgotten Warden em 80% dos zoos: vida do zoo + Spirit Vessel grátis.
A8: Luvas | B8: Vida/resists/atributos | C8: Treefingers (Giant's Blood) se usar maça de 2 mãos | D8: Treefingers até ter Giant's Blood na árvore; depois rare de Evasion/Deflection com vida e resist | E8: Vida; resist; atributos | F8: Dano de player aqui é desperdício.
A9: Botas | B9: 10–20% MS (campanha), 25% no Ato 4 | C9: 30% MS + vida + resist | D9: 30% MS + Evasion/Deflection + resists | E9: Movement Speed SEMPRE primeiro | F9: Idol filler aqui já conta para a Idolatry.
A10: Amuleto | B10: Atributos / resists | C10: +Minion Skills + atributos | D10: +2/+3 Minion Skills + anoint Warlord Leader | E10: Minion Skills; atributos; resist
A11: Anéis | B11: Vida/resists/atributos | C11: Ventor's Gamble com resists positivas (+vida +Spirit) | D11: Kalandra's Touch copiando um rare perfeito | E11: Cap de resist; atributos | F11: Anéis são o lugar mais barato para fechar resist.
A12: Cinto | B12: Meginord's Girdle (Strength + frio) ou raro vida/resist | C12: Rare vida/resist ou Darkness Enthroned (Idols) | D12: Darkness Enthroned · Mageblood (luxo) | E12: Vida; resist; atributos | F12: Darkness Enthroned é CINTO (a planilha antiga dizia capacete).
A13: Jewels | B13: Emerald: Companion dano/vida; Sapphire: Minion +% Elemental Res | C13: From Nothing (~0,21 div) + Sapphires de minion crit | D13: From Nothing + Prism of Belief +2/+3 + Megalomaniac/Heart of the Well | E13: Minion crit/dano > attack speed > resist de minion | F13: Prism de roll ruim não vale só por ser unique.
A14: Charms | B14: Beira's Anguish · Sanguis Heroum · Arakaali's Gift (todos < 0,02 div) | C14: Nascent Hope · The Fall of the Axe | D14: Rite of Passage (luxo) | E14: Cobrir Burn / Poison / Bleed | F14: Com muita Evasion/Deflection, DoT é o que mata.
A15: Flasks | B15: Maior cura no menor tempo | C15: Lavianga's Spirits (mana constante) | D15: Lavianga's Spirits + life flask de recuperação instantânea | E15: Cura rápida
A17: ORDEM DE COMPRA — onde gastar primeiro
A18: # | B18: Item | C18: Fase | D18: Custo | E18: Impacto
A19: 1 | B19: Kit de leveling (Foxshade, Blackheart ×2, Goldrim, Wanderlust) | C19: Ato 1 | D19: Barato | E19: Campanha rápida
A20: 2 | B20: Rattling Sceptre + Trenchtimbre | C20: Ato 3 | D20: Barato | E20: Troca para minion
A21: 3 | B21: Chober Chaber + Treefingers | C21: Ato 3 | D21: Barato (~7 ex) | E21: O centro da build
A22: 4 | B22: The Vertex (versão Equipment) | C22: Ato 3 | D22: Valor (~0,4 div) | E22: Libera a Chober com sceptre
A23: 5 | B23: Enfolding Dawn (+100 Spirit) | C23: Ato 4 | D23: Barato | E23: Mais minions
A24: 6 | B24: Evergrasping Ring ×2 | C24: Ato 4 | D24: Barato | E24: Chaos para o zoo
A25: 7 | B25: Sylvan's Effigy + Primate/Rabbit Idol | C25: Nv 78 | D25: Valor (~1 div) | E25: Zoo ilimitado
A26: 8 | B26: Forgotten Warden + Lavianga's Spirits | C26: Nv 80 | D26: Valor (~0,3 div) | E26: Spirit Vessel + mana
A27: 9 | B27: Mageblood · Kalandra's Touch · Rite of Passage | C27: Endgame | D27: Luxo | E27: Teto

Sheet Spirit Planner
A1: SPIRIT PLANNER — cabe no seu Spirit?
A2: Amarelo = você edita. Estimativa: custo ÷ ((1 + increased) × more/less). Confira sempre o valor final no jogo.
A4: PARÂMETROS
A5: Spirit total | B5: =INÍCIO!B7 | C5: Vem do INÍCIO (B7).
A6: Trusted Kinship alocado? | B6: Sim | C6: 30% more eficiência p/ Companion · 20% less p/ o resto.
A7: Easy Going alocado? | B7: Sim | C7: +25% increased eficiência de Companion.
A8: Outros % increased eficiência (ex.: 0,10) | B8: 0 | C8: Jewels/itens. Digite como fração.
A9: Idolatry alocado? | B9: Não | C9: +2% eficiência por Idol.
A10: Nº de Idols equipados | B10: 0
A11: Increased (Companion) | B11: =IF(B7="Sim",0.25,0)+B8+IF(B9="Sim",0.02*B10,0)
A12: Increased (Outros) | B12: =B8+IF(B9="Sim",0.02*B10,0)
A13: Multiplicador more/less (Companion / Outro) | B13: =IF(B6="Sim",1.3,1) | C13: =IF(B6="Sim",0.8,1)
A15: SEU ZOO (exemplo preenchido: Ato 4 barato — troque pelos seus valores)
A16: Skill / Companion | B16: Ativo? | C16: Tipo | D16: Custo base | E16: Unidade | F16: Spirit usado | G16: Nota
A17: Mighty Silverfist | B17: Sim | C17: Companion | D17: 47.4 | E17: % | F17: =IF(B17<>"Sim",0,IF(E17="%",D17/100*$B$5,D17)/IF(C17="Companion",(1+$B$11)*$B$13,(1+$B$12)*$C$13)) | G17: 47,4% antes de reduções (guia)
A18: Quadrilla (2º beast) | B18: Sim | C18: Companion | D18: 42.3 | E18: % | F18: =IF(B18<>"Sim",0,IF(E18="%",D18/100*$B$5,D18)/IF(C18="Companion",(1+$B$11)*$B$13,(1+$B$12)*$C$13)) | G18: 42,3% antes de reduções (guia)
A19: Wild Protector | B19: Sim | C19: Companion | D19: 0 | E19: Flat | F19: =IF(B19<>"Sim",0,IF(E19="%",D19/100*$B$5,D19)/IF(C19="Companion",(1+$B$11)*$B$13,(1+$B$12)*$C$13)) | G19: Digite o custo mostrado no jogo
A20: Wind Dancer | B20: Sim | C20: Outro | D20: 0 | E20: Flat | F20: =IF(B20<>"Sim",0,IF(E20="%",D20/100*$B$5,D20)/IF(C20="Companion",(1+$B$11)*$B$13,(1+$B$12)*$C$13)) | G20: Digite o custo base do jogo
A21: Discipline / Malice | B21: Não | C21: Outro | D21: 0 | E21: Flat | F21: =IF(B21<>"Sim",0,IF(E21="%",D21/100*$B$5,D21)/IF(C21="Companion",(1+$B$11)*$B$13,(1+$B$12)*$C$13)) | G21: Digite o custo base do jogo
A22: Withering Presence | B22: Não | C22: Outro | D22: 0 | E22: Flat | F22: =IF(B22<>"Sim",0,IF(E22="%",D22/100*$B$5,D22)/IF(C22="Companion",(1+$B$11)*$B$13,(1+$B$12)*$C$13)) | G22: Sofre o 'less' do Trusted Kinship
A23: Skeletal Cleric | B23: Não | C23: Outro | D23: 0 | E23: Flat | F23: =IF(B23<>"Sim",0,IF(E23="%",D23/100*$B$5,D23)/IF(C23="Companion",(1+$B$11)*$B$13,(1+$B$12)*$C$13))
A24: Vile Vulture | B24: Não | C24: Companion | D24: 45.3 | E24: % | F24: =IF(B24<>"Sim",0,IF(E24="%",D24/100*$B$5,D24)/IF(C24="Companion",(1+$B$11)*$B$13,(1+$B$12)*$C$13)) | G24: T15
A25: Rhex | B25: Não | C25: Companion | D25: 31.2 | E25: % | F25: =IF(B25<>"Sim",0,IF(E25="%",D25/100*$B$5,D25)/IF(C25="Companion",(1+$B$11)*$B$13,(1+$B$12)*$C$13)) | G25: Aura barata
A26: Outro | B26: Não | C26: Outro | D26: 0 | E26: Flat | F26: =IF(B26<>"Sim",0,IF(E26="%",D26/100*$B$5,D26)/IF(C26="Companion",(1+$B$11)*$B$13,(1+$B$12)*$C$13))
A28: Spirit reservado | B28: =SUM(F17:F26)
A29: Spirit livre | B29: =B5-B28
A30: Uso | B30: =IFERROR(B28/B5,0)
A31: Status | B31: =IF(B29<0,"ESTOUROU — desligue algo",IF(B30>0.9,"No limite","OK"))
A33: Assunção: custos '%' são % do Spirit máximo antes de reduções (conforme o guia imortilize). Os valores 'Flat' você copia do jogo. É uma estimativa — o painel de skills do jogo é a verdade final.

Sheet Companions & Beasts
A1: COMPANIONS & BEASTS — o que capturar
A2: Custo = % de Spirit antes de reduções. Prioridade de aura: Extra Physical ou Haste Aura > Energy Shield ou Invulnerability Aura > Temporal Bubble > Elemental Resistance Aura
A3: Beast | B3: Onde | C3: Papel | D3: Custo base | E3: Tier | F3: Mods desejados | G3: Supports | H3: Requer
A4: Mighty Silverfist / Zekoa | B4: Ato 3 Jungle Ruins / mapas Riverside e Rupture | C4: Único DPS de verdade | D4: 0.474 | E4: S+ | F4: Extra Crits · Hasted · Extra Damage as Chaos/Physical | G4: Feeding Frenzy II · Rage III · Muster · Heft · Rapid Attacks II | H4: Tame Beast + The Natural Order
A5: Quill Crab (Porcupine) | B5: Ato 4 Whakapanu Island (essence e raros na praia) | C5: Aura bot barato | D5: 0.249 | E5: S | F5: Haste Aura (o mais fácil de achar) | G5: Loyalty · Last Gasp · Elemental Army · Meat Shield II · Minion Mastery | H5: Tame Beast
A6: Coconut Crab | B6: Ato 4 Whakapanu Island | C6: Aura bot barato | D6: 0.249 | E6: S | F6: Haste / Physical Aura | G6: Loyalty · Last Gasp · Elemental Army · Meat Shield II · Minion Mastery | H6: Tame Beast
A7: Swarming Wisp | B7: Ato 5 Ashen Forest (essence) | C7: Aura bot mais barato | D7: 0.21 | E7: S | F7: Qualquer aura T1 exceto Haste | G7: Loyalty · Last Gasp · Elemental Army · Meat Shield II · Minion Mastery | H7: Tame Beast
A8: Plague Swarm | B8: Ato 2 Mawdun Quarry (essence) | C8: Aura bot mais barato | D8: 0.21 | E8: A+ | F8: Aura T1 | G8: Loyalty · Last Gasp · Elemental Army · Meat Shield II · Minion Mastery | H8: Tame Beast
A9: Crag Leaper | B9: Ato 2 Vastiri Outskirts (essence) | C9: Aura bot | D9: 0.231 | E9: A+ | F9: Aura T1 (NUNCA Haste: é very_fast_movement) | G9: Loyalty · Last Gasp · Elemental Army · Meat Shield II · Minion Mastery | H9: Tame Beast
A10: Bramble Ape | B10: Ato 5 Kriar Village | C10: Aura bot | D10: 0.249 | E10: A | F10: Aura T1 | G10: Loyalty · Last Gasp · Elemental Army · Meat Shield II · Minion Mastery | H10: Tame Beast
A11: Rasp Scavenger | B11: Ato 5 Khari Crossing (essence) | C11: Aura bot reserva | D11: 0.267 | E11: A | F11: Aura T1 | G11: Loyalty · Last Gasp · Elemental Army · Meat Shield II · Minion Mastery | H11: Tame Beast
A12: Diretusk Boar | B12: Ato 3 Infested Barrens (garantido) | C12: Companion de campanha | D12: 0.39 | E12: A | F12: Qualquer | G12: Loyalty · Muster · Rapid Attacks II · Minion Mastery | H12: Tame Beast
A13: Antlion Charger | B13: Ato 3 Infested Barrens (garantido) | C13: Companion de campanha (setup de 3 do Mattjestic) | D13: 0.423 | E13: A | F13: Qualquer | G13: Loyalty · Last Gasp | H13: Tame Beast
A14: Azmerian Wolf | B14: Vem no Sylvan's Effigy | C14: 2º dano | D14: — | E14: S | F14: — | G14: Feeding Frenzy II · Rapid Attacks II · Rage III · Hulking Minions/Muster · Loyalty | H14: Sylvan's Effigy
A16: LOOP DE CAPTURA
A17: Passo 1 | B17: Ache um beast raro/unique capturável.
A18: Passo 2 | B18: Pause (atalho do Marketplace no botão do meio) e leia os mods antes de bater.
A19: Passo 3 | B19: Se não servir, siga em frente; se servir, use Tame Beast com ele em vida baixa.
A20: Passo 4 | B20: Compare a reserva no Spirit Planner: aura boa que estoura Spirit piora o setup.
A21: Passo 5 | B21: Suba a gem Tame Beast e coloque supports de sobrevivência (Meat Shield II, Loyalty).

Sheet Ascendência & Árvore
A1: ASCENDÊNCIA & ÁRVORE DE PASSIVAS
A2: Ordem obrigatória: Wild Protector → The Natural Order → The Catha's Balance → Idolatry. Texto dos nós conforme PoE2DB.
A3: # | B3: Nó | C3: Quando | D3: O que faz | E3: Por que
A4: 1 | B4: Wild Protector | C4: Ato 2 · Trial of the Sekhemas | D4: Invoca o Bear Spirit: salta nos inimigos com Maim, faz leech de vida no slam e dá Intimidate. Não conta no limite de companions. | E4: Tank grátis na campanha e base de Presence.
A5: 2 | B5: The Natural Order | C5: Ato 3 · Trial of Chaos | D5: Tame Beast pode capturar Unique Beasts (1 por vez). Unique tamed ganha 30% movement speed e é possuído por Azmeri Spirits aleatórios a cada 20s. | E5: Libera o Mighty Silverfist — nenhuma outra classe usa.
A6: 3 | B6: The Catha's Balance | C6: Atlas · Trial nível 60+ | D6: Companions causam dano de ataque adicional igual a 60% do dano da sua arma main-hand. | E6: Maior salto de dano da build. Arma de maior dano por golpe vence, independente de attack speed.
A7: 4 | B7: Idolatry | C7: Atlas · Trial nível 75+ | D7: +10% dano de companions e +2% reservation efficiency por Idol equipado; -4% em todas as resists por Augment que não é Idol. | E7: Escala dano e Spirit com Idols. Pegue só quando não depender de runas/soul cores para resist.
A9: PASSIVAS-CHAVE
B10: Nó | C10: Tipo | D10: O que faz | E10: Por que | F10: Quando
B11: Trusted Kinship | C11: Keystone | D11: 2 companions de tipos diferentes; 30% more eficiência de reserva de Companion; 20% less para as demais. | E11: Mesmo com o Effigy, os 30% more de eficiência continuam valendo. | F11: Ato 3 → sempre
B12: Giant's Blood | C12: Keystone | D12: Maças/machados/espadas de 2 mãos em uma mão; triplica requisitos de atributo das armas. | E12: Chober Chaber + sceptre ao mesmo tempo. | F12: Treefingers no Ato 3 → árvore no endgame
B13: Easy Going | C13: Notable | D13: 25% increased reservation efficiency de Companion. | E13: Mais companions no mesmo Spirit. | F13: Ato 4
B14: Polymathy | C14: Notable | D14: Atributos. | E14: Ajuda com os requisitos triplicados. | F14: Giant's Blood
B15: Mind Over Matter | C15: Keystone | D15: Todo dano sai da mana antes da vida; 50% less recuperação de mana. | E15: Com +100 mana da Chober e Lavianga's Spirits vira uma camada de defesa enorme. | F15: Endgame (nv 90+)
A17: ÁRVORE POR ETAPA
A18: Nível | B18: Foco | C18: Dano | D18: Defesa | E18: Spirit | F18: Não faça
A19: 1–30 | B19: Twister/projétil | C19: Twister | D19: Vida + Evasion | E19: — | F19: Minion cedo demais
A20: 31–45 | B20: Trusted Kinship + Bonds (Mamba, Cat) + Unspoken Bond | C20: Macaco | D20: Blur, Catlike Agility, Escape Velocity | E20: Trusted Kinship | F20: Nós de ataque
A21: 46–64 | B21: Easy Going, Inspiring Ally, Bond of the Wolf/Owl | C21: Macaco + Muster | D21: Evasion | E21: Easy Going | F21: Sacrificar resists
A22: 65–77 | B22: Sturdy Ally, Captivating Companionship, Sic 'Em, Howling Primate | C22: Catha + Chober | D22: Enhanced Reflexes | E22: Mais companions | F22: Julgar arma por DPS
A23: 78–89 | B23: Giant's Blood, Polymathy, Deflection, Long Distance Relationship | C23: Zekoa + Azmerian Wolf | D23: Enduring/Avoiding Deflection | E23: Effigy | F23: Tirar Trusted Kinship
A24: 90+ | B24: Mind Over Matter, The Soul Meridian, Beastial Skin | C24: Zoo inteiro | D24: MoM | E24: Idolatry | F24: MoM sem mana
A26: Dica: use o planner da Mobalytics (links em Fontes) para ver o caminho exato de cada ato — as cores Amarelo/Rosa/Verde são árvore principal / Weapon Set 1 / Weapon Set 2.

Sheet Quests
A1: RECOMPENSAS PERMANENTES — não pule
A2: +130 Spirit, resistências e weapon set points ao longo da campanha. Marque Feito.
A3: Ato | B3: Área | C3: Boss / Quest | D3: Recompensa | E3: Prioridade | F3: Status
A4: Ato 1 | B4: Clearfell | C4: Beira of the Rotten Pack | D4: +10% resistência a frio | E4: Alta | F4: Pendente
A5: Ato 1 | B5: Hunting Grounds | C5: The Crowbell | D5: 2 Weapon Set Passive Points | E5: Alta | F5: Pendente
A6: Ato 1 | B6: Freythorn | C6: The King in the Mists | D6: +30 Spirit | E6: CRÍTICA | F6: Pendente
A7: Ato 1 | B7: Ogham Farmlands | C7: Una's Hut | D7: 2 Weapon Set Passive Points | E7: Alta | F7: Pendente
A8: Ato 1 | B8: Ogham Manor | C8: Candlemass, the Living Rite | D8: +20 vida máxima | E8: Alta | F8: Pendente
A9: Ato 2 | B9: Keth | C9: Kabala, Constrictor Queen | D9: 2 Weapon Set Passive Points | E9: Alta | F9: Pendente
A10: Ato 2 | B10: Valley of the Titans | C10: Medallion | D10: +1 Charm Slot e 30% charm charges | E10: Alta | F10: Pendente
A11: Ato 2 | B11: Deshar | C11: Final Letter | D11: 2 Weapon Set Passive Points | E11: Alta | F11: Pendente
A12: Ato 2 | B12: Spires of Deshar | C12: Sisters of Garukhan | D12: +10% resistência a raio | E12: Alta | F12: Pendente
A13: Ato 3 | B13: Jungle Ruins | C13: Mighty Silverfist | D13: 2 Weapon Set Points + alvo do Tame | E13: CRÍTICA | F13: Pendente
A14: Ato 3 | B14: Venom Crypts | C14: Venom Draught | D14: 25% Stun Threshold | E14: Média | F14: Pendente
... A32: Interlúdio | B32: Howling Caves | C32: The Abominable Yeti | D32: 2 Weapon Set Passive Points | E32: Alta | F32: Pendente

Sheet Tricks Pro
A1: TRICKS DE PROFISSIONAL
A2: O que streamers e jogadores de topo fazem para ganhar tempo, dano e segurança.
A3: Categoria | B3: Nível | C3: Trick | D3: Como fazer
A4: Captura | B4: Fácil | C4: Limite de companions | D4: Base: 1 companion. Trusted Kinship (keystone) ou Yriel's Fostering (body): 2 companions de TIPOS diferentes — não somam entre si. Sylvan's Effigy: qualquer número de tipos diferentes. O urso do Wild Protector não conta no limite.
A5: Captura | B5: Médio | C5: Rota de aura bots do Mattjestic | D5: Antes do Sylvan's Effigy só cabe 1 beast de aura (limite de 2 companions com Trusted Kinship). 1) Ato 4 Whakapanu Island: essence de crabs na praia (Quill/Coconut Crab ~25%) até achar Haste Aura. 2) Ato 5 Ashen Forest: Swarming Wisp (21%) com qualquer aura T1 exceto Haste. 3) Ato 2 Vastiri Outskirts: Crag Leaper (23,1%). Guarde auras T1 diferentes e substitua crabs duplicados. Os beasts extras entram quando você equipar o Effigy.
A6: Captura | B6: Fácil | C6: Haste não aparece em beasts muito rápidos | D6: Beasts com a tag very_fast_movement (ex.: Crag Leaper) nunca rolam Haste Aura. Procure Haste em crabs.
A7: Dano | B7: Médio | C7: Conte os tipos de minion para o Muster | D7: Urso, macaco, cada beast diferente, Azmerian Wolf, Wolf Pack, Spirit Vessel e cada tipo de esqueleto contam como um tipo. Cada um soma 7% more dano nos companions com Muster.
A8: Spirit | B8: Fácil | C8: Rattling Sceptre já traz o esqueleto | D8: O Rattling Sceptre é uma base comum (não unique) que já traz a gem Skeletal Warrior. Um único esqueleto basta como alvo do Pain Offering até o Effigy; o segundo só quando sobrar Spirit.
A9: Economia | B9: Fácil | C9: The Vertex: confira a versão | D9: Só a versão com 'Equipment has no Attribute Requirements' libera a Chober Chaber com Giant's Blood. Filtre por esse mod no trade.
A10: Dano | B10: Médio | C10: Pain Offering sem cair no boss | D10: Brutus' Brain no Pain Offering deixa o espinho imune a dano, então o buff não some quando o boss acerta a área. Danse Macabre precisa de 2 esqueletos vivos: só coloque quando o Spirit permitir o 2º esqueleto (Interlúdios). Depois do Effigy, o Skeletal Cleric com Sacrificial Lamb II vira o alvo.
A11: Captura | B11: Fácil | C11: Como o Tame Beast funciona | D11: Use o Tame Beast num raro: ele fica envolto em wisps (Hinder) por ~8–12s. Mate enquanto os wisps estão nele para capturar. O beast guarda até 4 mods de monstro, então capture o que tem os mods que você quer.
A12: Silverfist | B12: Médio | C12: Zekoa com 3+ mods | D12: Riverside ou Rupture + 1 Cruel Hegemony + 2 tablets raros com 'Unique Monsters have 1 additional Rare Modifier'. Ordem de mods: Extra Crits > Hasted > Extra Damage as Chaos/Physical > Soul Eater.
A13: Silverfist | B13: Avançado | C13: Reroll de mods morrendo (softcore) | D13: Com Doryani como Atlas Master e o nó Stitch the Flesh (revive extra), dá para morrer de propósito na luta e o boss volta com mods novos. Rituals perto de City biomes geram vários Zekoas no mesmo map.
A14: Dano | B14: Médio | C14: Giant's Blood + The Vertex | D14: Treefingers dá Giant's Blood (maça 2 mãos + sceptre), mas triplica requisitos. The Vertex remove requisitos de gems (e, em algumas versões, do equipamento). Soul Core of Cholotl converte 40% para Dex.
... A39: Economia | B39: Fácil | C39: Compre a Chober Chaber cedo | D39: A Chober Chaber costuma custar poucos Exalts. Compre já Runeforged no Ato 3–4 e guarde: com a Catha's Balance ela vira a principal fonte de dano do zoo.

Sheet Diagnóstico
A1: DIAGNÓSTICO — o dano caiu? algo deu errado?
A2: Sintoma → causa provável → correção. Abaixo, análise do seu setup atual (imagens da planilha antiga).
A3: Sintoma | B3: O que fazer
A4: O zoo parou de bater / sumiu | B4: Spirit acima do limite desliga skills. Veja a reserva no painel de skills e desligue uma não-companion.
A5: Dano caiu depois de trocar arma | B5: A Catha's Balance usa a main-hand do set ativo. Volte para o set com a arma forte.
A6: Silverfist fraco no Ato 4 | B6: Confira os supports do macaco: Feeding Frenzy II · Rage II · Rapid Attacks II · Heft (Muster só entra nos Interlúdios, quando tiver vários tipos de minion). Suba o nível da gem Tame Beast e use Sniper's Mark no boss.
A7: Resists caíram do nada | B7: Idolatry: -4% por Augment que não é Idol. Troque runas/soul cores por Idols ou recapar via gear.
A8: Morro para bleed/burn/poison | B8: Charms Staunching / Ruby / Antidote e resist de chaos. Evasion não protege contra DoT.
A9: Bosses demoram | B9: Sniper's Mark no boss, Armour Break III no macaco, e confira se os companions estão na sua Presence.
A10: Tirei Trusted Kinship com o Effigy e o Spirit estourou | B10: Recoloque o keystone: os 30% more de reservation efficiency continuam valendo mesmo com companions ilimitados.
A11: Não consigo equipar a Chober Chaber com Giant's Blood | B11: Os requisitos triplicam. Use The Vertex, Soul Core of Cholotl (40% vira Dex) ou atributos na árvore.
A12: Zekoa com poucos mods | B12: Use tablets com 'Unique Monsters have 1 additional Rare Modifier' + Cruel Hegemony em Riverside/Rupture.
A13: Pain Offering não dá buff | B13: Ele precisa de um esqueleto vivo por perto (Warrior, Arsonist, Sniper ou Cleric) com Sacrificial Lamb. Danse Macabre precisa de 2 esqueletos: com 1 só, troque por Sacrificial Offering.
A14: Mana acaba no endgame | B14: Lavianga's Spirits (flask constante) + a mana da Chober Chaber; com Mind Over Matter a mana também é sua defesa.
A15: Não cabe tudo no Spirit | B15: Ative na ordem da aba Skills: macaco → beast de aura → Withering Presence → 1 esqueleto. Curses, marks, Pain Offering e Unearth não reservam Spirit. Se o painel mostrar Spirit negativo, desligue o último minion que entrou.
A17: SEU SETUP ATUAL — análise
A18: Silverfist — Feeding Frenzy II, Rage II, Rapid Attacks II, Heft, Muster | B18: Certo: é exatamente o setup do Mattjestic (Act 5 / mapping). Com Rage III no lugar do Rage II a partir do mapping.
A19: Wild Protector — Magnified Area I, Armour Break III, Minion Splash II | B19: Certo para Ato 4 → mapping T1-10 (o Mattjestic usa os mesmos três e adiciona Minion Mastery). No endgame vira Romira's Requital + Catha's Brilliance.
A20: Pain Offering — Danse Macabre, Prolonged Duration II | B20: Central na rota. Danse Macabre só funciona com 2 esqueletos vivos; com 1 esqueleto (Ato 3–4) use Sacrificial Offering no lugar. Brutus' Brain entra no endgame (o espinho não morre).
A21: Skeletal Sniper + Withering Presence | B21: Os dois fazem sentido: o Sniper conta como mais um tipo de minion para o Muster e serve de alvo do Pain Offering; o Withering Presence vale com 2× Evergrasping Ring (dano de chaos nos aliados). Sem os anéis, troque o Withering Presence.

Sheet Atlas
A1: ATLAS — checklist e árvore
A2: Da entrada no T1 até Uber Arbiter. Nós do Atlas conforme o guia T15+ (0.5.5).
A3: Etapa | B3: Meta | C3: Upgrade-chave
A4: Antes do T1 | B4: 75% resists · 25–30% MS · Silverfist com sockets | C4: Catha's Balance se já tiver
A5: T1–T5 | B5: Zero mortes aleatórias · +Minion ranks | C5: Sceptre raro com Spirit
A6: T6–T10 | B6: Bosses rápidos · main-hand de alto dano | C6: Deflection começando
A7: T11–T15 | B7: Zoo estável · charms de DoT | C7: Chober Chaber + Rattling Sceptre (ou Sylvan's Effigy)
A8: T15+ Value | B8: Lazy clear · Azmerian Wolf / Wolf Pack | C8: Sylvan's Effigy + Idolatry
A9: Arbiter / Uber | B9: Mana Remnants · aura beasts · 350 Spirit | C9: From Nothing / Prism of Belief
A11: ÁRVORE DO ATLAS
A12: Grupo | B12: Nó
A13: Standard | B13: Unseen Rivers: Vivid
A14: Standard | B14: Craftsman's Creed: Skill of Hand
A15: Standard | B15: Well-equipped Opponents: Dexterity
A16: Standard | B16: Blood on the Stones: Bosses
A17: Standard | B17: Divined Blessing: Seeking Shrine
A18: Standard | B18: The Chosen Path: Azmeri Spirits
A19: Standard | B19: Sacred Sap: Commingled
A20: Standard | B20: Overlord's Influence: Azmeri Spirit
A21: Standard | B21: Overlord's Domain: Essence
A22: Standard | B22: The Journey Ahead: Effectiveness
A23: Standard | B23: Avatar of Evolution
... A46: Vaal Temple | B46: Atziri's Assets: Designs

Sheet Otimizações & Meta
A1: NOSSA ROTA OTIMIZADA — o que mudou e por quê
A2: Baseado em 5649 Spirit Walkers com Sylvan's Effigy + 24 zoos nível 98–99 da liga Forbidden Rites (poe.ninja, 15/09/2026).
A3: # | B3: Otimização | C3: Evidência (dados) | D3: Por quê | E3: Guia base dizia
A4: 1 | B4: Por que a Chober Chaber é o centro | C4: Mattjestic usa do 'Giant's Blood' ao 100m DPS; 24% dos zoos com Effigy no poe.ninja. | D4: A Catha's Balance dá aos companions 60% do dano da sua main-hand por golpe. A Chober é uma maça de 2 mãos com dano base enorme e ainda dá +2 a +4 Minion Skills, +50 Spirit e +100 mana. Nenhuma outra arma entrega tudo isso junto. | E4: Rotas antigas: Tyranny's Grip / spear rare.
A5: 2 | B5: Giant's Blood: 2 mãos + sceptre | C5: Keystone em todas as variantes endgame do Mattjestic; 34% dos zoos com Effigy. | D5: Sem Giant's Blood, a Chober ocuparia as duas mãos e você perderia o sceptre (Skeletal Warrior no começo, Sylvan's Effigy depois). Treefingers dá o keystone cedo; no endgame ele vai para a árvore.
A6: 3 | B6: The Vertex resolve os requisitos triplicados | C6: Variante 0.5.5 Mapping: 'The Vertex (equipment)'. | D6: Giant's Blood triplica os requisitos de atributo das armas marciais. A versão do The Vertex com 'Equipment has no Attribute Requirements' zera isso e libera a Chober já no Ato 3.
A7: 4 | B7: Pain Offering é central (não opcional) | C7: Presente em quase todas as variantes do Ato 3 ao 21m DPS. | D7: Espeta um esqueleto e dá aos minions próximos até +29% attack speed e +58% dano (mais 30% com Danse Macabre e 30% com Sacrificial Offering). Brutus' Brain impede o espinho de morrer. | E7: Eu tinha chamado de 'botão opcional' — estava errado.
A8: 5 | B8: Esqueletos existem para o Muster e para o Pain Offering | C8: Mattjestic (Ato 5) usa Warrior, Arsonist, Sniper, Frost Mage e Reaver sem supports de dano — mas só com Spirit sobrando. Entre um por vez. | D8: Muster: +7% more dano para CADA tipo diferente de minion que revive. Cada tipo de esqueleto que couber no Spirit soma +7% no macaco e ainda serve de alvo do Pain Offering. 1 de cada tipo basta.
A9: 6 | B9: Skeletal Cleric é alvo válido do Pain Offering | C9: Endgame: Cleric com Sacrificial Lamb II + Tecrod's Revenge. | D9: O Cleric é um esqueleto. Quando o Effigy tira o Rattling Sceptre, o Cleric (com Sacrificial Lamb II) vira o esqueleto espetado e ainda cura/revive. | E9: Eu tinha dito que o Cleric não servia — estava errado.
A10: 7 | B10: Withering Presence + Evergrasping Ring | C10: Ato 4–5 do Mattjestic: 2× Evergrasping Ring + Withering Presence. | D10: O anel faz os aliados ganharem 15–25% do dano como chaos extra; o Wither faz os inimigos receberem mais chaos. Juntos se multiplicam. Sem o anel, o Wither é fraco. | E10: Eu tinha mandado tirar o Withering Presence — só vale tirar se não usar o anel.
A11: 8 | B11: Sem Ball Lightning / Lightning Warp | C11: Nenhuma das 26 variantes usa. | D11: Eram mobilidade do jogador e não ajudam o macaco. O espaço vai para curse, marks, Pain Offering e Refutation. | E11: O guia antigo usava.
A12: 9 | B12: Mace Strike + Einhar's Beastrite não é dano | C12: Variantes endgame (13–24). | D12: O Mace Strike vem da própria Chober. Com Einhar's Beastrite ele só finaliza inimigos com vida baixa, e cada raro finalizado te dá 2 modificadores dele por 300 s (Haste, Extra Damage…).
A13: 10 | B13: Refutation + itens Runeforged | C13: Do mapping T1–10 ao endgame. | D13: Refutation gasta todo o seu Runic Ward para bloquear todos os hits por um tempo. Runic Ward vem de armaduras Runeforged/Runemastered — é por isso que as armaduras do Mattjestic são Runeforged.
A14: 11 | B14: Aura bots baratos em Spirit | C14: Tier-list do Mattjestic (0.5). | D14: Com Sylvan's Effigy, o objetivo são 2–3 auras T1 (antes dele só cabe 1) (Physical/Haste > ES/Invulnerability > Temporal Bubble > Elemental Res) em beasts de 21–25% de Spirit: Swarming Wisp, Crag Leaper, Quill/Coconut Crab. | E14: Beasts de 40%+ de Spirit.
A16: BODY ARMOUR (% de uso)
B17: Forgotten Warden | C17: 0.8
B18: Morior Invictus | C18: 0.11
B19: Rare | C19: 0.06
A21: MAIN-HAND (% de uso)
B22: Tyranny's Grip | C22: 0.39
B23: Trenchtimbre | C23: 0.26
B24: Chober Chaber | C24: 0.24
B25: The Hammer of Faith | C25: 0.06
A27: CONFIGURAÇÃO DE ARMAS (% de uso)
B28: Arma 1 mão / Sceptre | C28: 0.62
B29: Maça 2 mãos / Sceptre (Giant's Blood) | C29: 0.32
B30: Spear / Sceptre | C30: 0.02
A32: KEYSTONES (% de uso)
B33: Trusted Kinship | C33: 0.99
B34: Giant's Blood | C34: 0.34
B35: Mind Over Matter | C35: 0.27
B36: Iron Reflexes | C36: 0.04
B37: Chaos Inoculation | C37: 0.02
A39: ASCENDÊNCIA (% de uso)
B40: The Natural Order | C40: 1
B41: Wild Protector | C41: 0.99
B42: The Catha's Balance | C42: 0.97
B43: Idolatry | C43: 0.86
A45: COMPANIONS (SKILLS PRINCIPAIS) (% de uso)
B46: Wild Protector | C46: 0.99
B47: Azmerian Wolf | C47: 0.97
B48: Wolf Pack | C48: 0.84
B49: Zekoa, the Headcrusher | C49: 0.72
B50: Diretusk Boar | C50: 0.4
B51: Plague Harvester | C51: 0.29
B52: Quadrilla | C52: 0.26
B53: Mighty Silverfist | C53: 0.23
B54: Quill Crab | C54: 0.17
A56: SKILLS DE SPIRIT (% de uso)
B57: Discipline | C57: 1
B58: Spirit Vessel | C58: 0.8
B59: Skeletal Cleric | C59: 0.29
B60: Ghost Dance | C60: 0.24
A62: SUPPORTS MAIS USADOS (% de uso)
B63: Muster | C63: 0.98
B64: Rapid Attacks II | C64: 0.97
B65: Loyalty | C65: 0.96
B66: Feeding Frenzy II | C66: 0.93
B67: Rage III | C67: 0.91
B68: Romira's Requital | C68: 0.69
A70: ANOINTS DE AMULETO (% de uso)
B71: Warlord Leader | C71: 0.2
B72: Gigantic Following | C72: 0.13
B73: The Soul Meridian | C73: 0.11
B74: Relentless Fallen | C74: 0.05
B75: Lord of Horrors | C75: 0.04
B76: Vile Mending | C76: 0.03
A78: CHARMS / FLASKS ÚNICOS (% de uso)
B79: Beira's Anguish | C79: 0.43
B80: Nascent Hope | C80: 0.33
B81: Sanguis Heroum | C81: 0.26
B82: Lavianga's Spirits | C82: 0.25
B83: Arakaali's Gift | C83: 0.22
B84: The Fall of the Axe | C84: 0.12
B85: Rite of Passage | C85: 0.1
A87: JEWELS ÚNICOS (% de uso)
B88: From Nothing | C88: 0.21
B89: Prism of Belief | C89: 0.08
B90: Megalomaniac | C90: 0.07
B91: Heart of the Well | C91: 0.07
A93: ANÉIS ÚNICOS (% de uso)
B94: Ventor's Gamble | C94: 0.07
B95: Kalandra's Touch | C95: 0.06
B96: Andvarius | C96: 0.04
B97: Eshtera's Path | C97: 0.03
A99: SUPPORTS NO ZEKOA (% de uso)
B100: Muster | C100: 0.93
B101: Feeding Frenzy II | C101: 0.86
B102: Rapid Attacks II | C102: 0.86
B103: Rage III | C103: 0.75
A105: NOTABLES MAIS COMUNS (24 ZOOS TOP) (% de uso)
B106: Bond of the Wolf | C106: 0.92
B107: Inspiring Ally | C107: 0.88
B108: Bond of the Mamba | C108: 0.88
B109: Long Distance Relationship | C109: 0.75
B110: Lord of Horrors | C110: 0.75
B111: Blur | C111: 0.75
B112: The Soul Meridian | C112: 0.71
B113: Entropic Incarnation | C113: 0.67
B114: Grip of Evil | C114: 0.67
...

Sheet Uniques
A1: UNIQUES DA BUILD — preço real, uso no meta e quando entram
A2: Preços em Divine Orb (1 div ≈ 353 Exalted) no poe.ninja em 15/09/2026. 'Uso' = % dos zoos com Sylvan's Effigy. Filtre por Fase/Faixa.
B3: Unique | C3: Slot | D3: Faixa | E3: Preço (div) | F3: Uso | G3: Fase | H3: Por quê | I3: Mods principais | J3: Como / versões
B4: Splinter of Lorrata | C4: Main-hand | D4: Barato | E4: 0.003 | F4: — | G4: Ato 1 | H4: Leveling nível 1: sempre envenena. Troque pelo Skysliver no 16. | I4: Adds (2-3) to (6-8) Physical Damage Deal no Elemental Damage 20% increased Melee Strike Range with this weapon Any number of Poisons from this Weapon can affect a target at the same time Always Poison on Hit with this weapon
B5: Foxshade | C5: Body Armour | D5: Barato | E5: 0.006 | F5: — | G5: Ato 1 | H5: Leveling: +Evasion, +Dexterity e Movement Speed com vida cheia. | I5: +(50-70) to Evasion Rating +(20-30) to Dexterity 10% increased Movement Speed when on Full Life 100% increased Evasion Rating when on Full Life
B6: Surefooted Sigil | C6: Amuleto | D6: Barato | E6: 0.006 | F6: — | G6: Ato 1 | H6: Leveling: vida, Dexterity e dodge roll maior. | I6: +(40-60) to maximum Life +(5-15) to Dexterity +1 metre to Dodge Roll distance 50% increased Evasion Rating if you've Dodge Rolled Recently
B7: Blackheart | C7: Anel | D7: Barato | E7: 0.009 | F7: — | G7: Ato 1 | H7: Leveling: dano de chaos nos ataques, regen de vida e Intimidate. Use dois. | I7: (3-6) Life Regeneration per second Adds (4-6) to (8-10) Chaos Damage to Attacks +(10-20)% of Armour also applies to Chaos Damage 25% chance to Intimidate Enemies for 4 seconds on Hit
B8: Wanderlust | C8: Botas | D8: Barato | E8: 0.014 | F8: — | G8: Ato 1 | H8: Leveling: 20% Movement Speed e imune a Slow. | I8: 20% increased Movement Speed +(10-20) to maximum Energy Shield +5 to Dexterity Your speed is unaffected by Slows
B9: Goldrim | C9: Capacete | D9: Barato | E9: 0.028 | F9: — | G9: Ato 1 | H9: Leveling: +25–35% todas as resistências. | I9: +(30-50) to Evasion Rating 10% increased Rarity of Items found +(25-33)% to all Elemental Resistances
B10: Meginord's Girdle | C10: Cinto | D10: Barato | E10: 0.009 | F10: — | G10: Ato 2 | H10: +40–50 Strength e resist a frio: resolve requisitos de supports na campanha. | I10: +(40-50) to Strength +(10-15)% to Cold Resistance 50% increased Flask Charges used 100% increased Flask Charges gained | J10: ≈ 0,009 div
B11: Skysliver | C11: Main-hand | D11: Valor | E11: 0.106 | F11: — | G11: Ato 2 | H11: Leveling: spear de raio com attack speed para o Twister no Ato 2. | I11: No Physical Damage Adds 1 to (80-120) Lightning Damage (15-30)% increased Attack Speed (50-100)% increased chance to Shock Rolls only the minimum or maximum Damage value for each Damage Type
B12: Midnight Braid | C12: Cinto | D12: Barato | E12: 0.003 | F12: — | G12: Ato 3 | H12: 50% do dano recebido é recuperado como mana, +resistências e +mana: sustenta Pain Offering, Unearth e marks. | I12: +(30-50) to maximum Mana +(5-10)% to all Elemental Resistances 50% of Damage taken Recouped as Mana
B13: Chober Chaber | C13: Main-hand (2 mãos) | D13: Barato | E13: 0.006 | F13: 0.24 | G13: Ato 3 | H13: O centro da rota. Maça de 2 mãos: dano base altíssimo (a Catha's Balance passa 60% dele por golpe para os companions), +2 a +4 Minion Skills, +50 Spirit e +100 mana. Custa ~2 Exalts. | I13: +100 Intelligence Requirement Adds (58-65) to (102-110) Physical Damage +(80-100) to maximum Mana +50 to Spirit +2 to Level of all Minion Skills Increases and Reductions to Minion Damage also affect you | J13: Runeforged (nv 55) ≈ 0,04 div · Para usar com sceptre precisa de Giant's Blood (Treefingers no começo, keystone na árvore depois). Giant's Blood TRIPLICA os requisitos de atributo: resolva com The Vertex (versão 'Equipment has no Attribute Requirements').
B14: Umbilicus Immortalis | C14: Cinto | D14: Barato | E14: 0.006 | F14: — | G14: Ato 3 | H14: Seu life flask também cura os minions, e eles não morrem enquanto o flask estiver ativo. Salva o macaco em bosses difíceis da campanha. | I14: (30-40)% reduced Flask Effect Duration +(20-30) to Intelligence Minions have (20-30)% increased maximum Life Your Life Flask also applies to your Minions Minions cannot Die while affected by a Life Flask (20-30)% increased Flask Charges gained | J14: · Alternativa ao Midnight Braid.
B15: Treefingers | C15: Luvas | D15: Barato | E15: 0.014 | F15: 0.03 | G15: Ato 3 | H15: Luvas de nível 11 que dão Giant's Blood por ~5 Exalts: permitem Chober Chaber + Rattling Sceptre já no Ato 3, sem gastar pontos na árvore. | I15: (30-60)% increased Armour Adds (6-10) to (12-16) Physical Damage to Attacks 5% reduced Attack Speed +(15-20) to Strength (20-30)% increased Stun Buildup Giant's Blood | J15: ≈ 0,014 div · Use enquanto não tiver luvas melhores; depois pegue o keystone na árvore.
B16: Trenchtimbre | C16: Main-hand | D16: Barato | E16: 0.023 | F16: 0.26 | G16: Ato 3 | H16: Modo barato: +1 Minion Skills na mão enquanto você não compra a trinca Chober + Treefingers + The Vertex. O Mattjestic usa com Rattling Sceptre do Ato 3 ao mapping T1–10. | I16: Adds (13-15) to (22-25) Physical Damage (20-30)% increased Attack Speed +1 to Level of all Minion Skills Increases and Reductions to Minion Attack Speed also affect you | J16: Runeforged (nv 40) ≈ 0,08 div · Base custa quase nada; equipe logo depois de capturar o Silverfist.
B17: The Vertex | C17: Capacete | D17: Valor | E17: 0.408 | F17: 0.13 | G17: Ato 3 | H17: Com Giant's Blood, os requisitos da Chober Chaber triplicam (centenas de Strength/Intelligence). A versão 'Equipment has no Attribute Requirements' zera isso. É a peça que libera a Chober cedo. | I17: Has no Attribute Requirements (100-150)% increased Evasion and Energy Shield (20-30)% increased Critical Hit Chance +(13-17)% to Chaos Resistance Equipment has no Attribute Requirements Skill Gems have no Attribute Requirements | J17: ≈ 0,41 div · Compre SÓ a versão com 'Equipment has no Attribute Requirements' (o Mattjestic marca como 'The Vertex (equipment)').
B18: Arakaali's Gift | C18: Charm | D18: Barato | E18: 0.003 | F18: 0.22 | G18: Ato 4 | H18: Contra poison: recupera vida e mana ao usar. | I18: Recover Life equal to (15-20)% of Mana Flask's Recovery Amount when used Recover Mana equal to (15-20)% of Life Flask's Recovery Amount when used | J18: ≈ 0,003 div
B19: Enfolding Dawn | C19: Body Armour | D19: Barato | E19: 0.003 | F19: — | G19: Ato 4 | H19: +100 Spirit num body de nível 1. É o maior ganho de Spirit da campanha: cabe mais um companion (ou o beast de aura mais cedo). | I19: (50-100)% increased Armour and Energy Shield +100 to Spirit +(5-15)% to all Elemental Resistances Gain no inherent bonus from Intelligence | J19: · Use do Ato 2 até o Forgotten Warden.
B20: Bushwhack | C20: Botas | D20: Barato | E20: 0.005 | F20: — | G20: Ato 4 | H20: 15–25% Movement Speed com Evasion, e seu dano físico dá Pin. Botas baratas com MS para a campanha. | I20: (15-25)% increased Movement Speed (50-80)% increased Evasion Rating +(10-20) to Dexterity Physical Damage is Pinning
B21: Sanguis Heroum | C21: Charm | D21: Barato | E21: 0.006 | F21: 0.26 | G21: Ato 4 | H21: Contra bleed: ganha cargas sozinho e cria Consecrated Ground. | I21: Gains (0.15-0.2) Charges per Second Creates Consecrated Ground on use | J21: ≈ 0,006 div
B22: Evergrasping Ring | C22: Anel | D22: Barato | E22: 0.006 | F22: — | G22: Ato 4 | H22: Aliados na sua Presence ganham 15–25% do dano como chaos EXTRA. Com dois anéis e Withering Presence/Despair, o zoo inteiro bate muito mais. | I22: +(60-100) to maximum Mana Allies in your Presence Gain (15-25)% of Damage as Extra Chaos Damage Enemies in your Presence Gain (6-12)% of Damage as Extra Chaos Damage | J22: · Use dois (um em cada mão) do Ato 4 ao mapping.
B23: Starkonja's Head | C23: Capacete | D23: Barato | E23: 0.008 | F23: 0.04 | G23: Ato 4 | H23: 15% do dano de hits vai para o companion antes de você. Defesa barata na campanha e no início dos maps. | I23: (100-180)% increased Evasion Rating (15-24)% increased Critical Hit Chance +(30-40) to Dexterity 150% increased Global Evasion Rating when on Low Life 15% of Damage from Hits is taken from your Damageable Companion's Life before you | J23: ≈ 0,01 div
B24: Beira's Anguish | C24: Charm | D24: Barato | E24: 0.011 | F24: 0.43 | G24: Ato 4 | H24: Contra ignite: cria chão em chamas que queima com 500% da sua vida máxima. | I24: (20-25)% Chance to gain a Charge when you kill an enemy Creates Ignited Ground for 4 seconds when used, Igniting enemies as though dealing Fire damage equal to 500% of your maximum Life | J24: ≈ 0,01 div
B25: Ventor's Gamble | C25: Anel | D25: Barato | E25: 0.028 | F25: 0.07 | G25: Interlúdios | H25: Até +80 vida e +20 Spirit (e resists aleatórias). Um bom roll custa quase nada. | I25: +(1-80) to maximum Life +(1-20) to Spirit (1-25)% increased Rarity of Items found (1-25)% reduced Rarity of Items found (-40-39)% to Fire Resistance (-40-39)% to Cold Resistance +(-39-40)% to Lightning Resistance | J25: ≈ 0,03 div · Compre um com resists positivas.
B26: Alpha's Howl | C26: Capacete | D26: Valor | E26: 0.418 | F26: 0.01 | G26: Início do Atlas | H26: +100 Spirit e Presence em dobro (auras e bônus de Presence alcançam o zoo espalhado). Resolve o Spirit do modo barato. | I26: (80-100)% increased Evasion Rating +100 to Spirit +(50-74)% to Cold Resistance Presence Radius is doubled | J26: ≈ 0,42 div · Troca o +Minion Skills do capacete por Spirit: vale enquanto faltar reserva.
B27: Undying Hate | C27: Jewel | D27: Valor | E27: 0.529 | F27: — | G27: Início do Atlas | H27: Timeless Jewel: conquista nós no raio com bônus Abyssal. Usado no mapping T1–10 do Mattjestic. | I27: Historic Conquered Attribute Passive Skills also grant +2 to Tribute | J27: · Opcional.
B28: Sylvan's Effigy | C28: Offhand | D28: Valor | E28: 0.952 | F28: 1 | G28: Início do Atlas | H28: Companions ilimitados (tipos diferentes), Azmerian Wolf e Discipline de graça, +50–68% Spirit. Nesta liga custa ~1 div: não é luxo, é o primeiro grande objetivo do Atlas. | I28: (50-68)% increased Spirit Allies in your Presence Regenerate (51.4-99.1) Life per second +(6-12) to all Attributes Companions deal (50-98)% increased damage to your Marked targets You can have any number of Companions of different types | J28: ≈ 0,95 div (4 mil à venda) · Coloque Primate Idol (+40% dano de aliados) e Rabbit Idol (+15% Spirit) nos sockets.
B29: Spiteful Floret | C29: Weapon set 2 | D29: Barato | E29: 0.003 | F29: 0.04 | G29: T15+ (Effigy) | H29: Fica no weapon set 2 só para conceder Sanguine Revelry (Remnants dão Rage e vida). Você não troca de set para lutar. | I29: (60-90)% increased Physical Damage (6-10)% increased Attack Speed +(7-14) to Strength (20-30)% chance to cause Bleeding on Hit Every 5 Rage also grants 5% of Damage taken Recouped as Life | J29: · Equipe no set 2 e ative Sanguine Revelry.
B30: Darkness Enthroned | C30: Cinto | D30: Barato | E30: 0.014 | F30: 0.02 | G30: T15+ (Effigy) | H30: Sockets de Augment tratados como Capacete/Escudo/Botas/Luvas com 50–99% mais efeito: mais Idols para a Idolatry. | I30: (50-99)% increased effect of Socketed Augment Items This item gains bonuses from Socketed Items as though it was a Helmet This item gains bonuses from Socketed Items as though it was a Shield This item gains bonuses from Socketed Items as though it was Boots This item gains bonuses from Socketed Items as though it was Gloves | J30: ≈ 0,014 div
B31: The Hammer of Faith | C31: Main-hand (2 mãos) | D31: Valor | E31: 0.101 | F31: 0.06 | G31: T15+ (Effigy) | H31: Giant Maul com 300–342% dano físico: muito dano por golpe para a Catha. Runeforged dá 30% phys como lightning e +60% dano de minion (bonded). | I31: (300-339)% increased Physical Damage 10% reduced Attack Speed +10% to all Elemental Resistances 50% increased Mana Regeneration Rate Every 10 seconds, gain a random non-damaging Shrine buff for 20 seconds | J31: ≈ 0,10 div · Também exige Giant's Blood para usar com sceptre.
B32: Nascent Hope | C32: Charm | D32: Valor | E32: 0.106 | F32: 0.33 | G32: T15+ (Effigy) | H32: Thawing Charm que ganha cargas ao matar e inicia recarga de ES ao usar. | I32: (20-25)% Chance to gain a Charge when you kill an enemy Energy Shield Recharge starts on use | J32: ≈ 0,11 div
B33: Lavianga's Spirits | C33: Flask | D33: Valor | E33: 0.106 | F33: 0.25 | G33: T15+ (Effigy) | H33: Flask de mana com efeito constante: sustenta os Commands do Azmerian Wolf e marks, e combina com Mind Over Matter. | I33: This Flask cannot be Used but applies its Effect constantly (70-80)% reduced Amount Recovered | J33: ≈ 0,11 div
B34: Forgotten Warden | C34: Body Armour | D34: Valor | E34: 0.209 | F34: 0.8 | G34: T15+ (Effigy) | H34: 80% dos zoos usam. Companions +30–50% vida, Deflection, 10–15% do dano deflectido vai para os companions, e concede Spirit Vessel nível 16 (um companion a mais sem gastar gem). | I34: +(70-100) to Deflection Rating per 50 missing Energy Shield (200-271)% increased Evasion and Energy Shield +(20-30) to Dexterity Companions have (30-50)% increased maximum Life (10-15)% of Damage from Deflected Hits is taken from Damageable Companion's Life before you | J34: Base ≈ 0,21 div · Runemastered ≈ 5 div · Soquete Fox Idol (ativa bonded) e uma skill de Bear/Werewolf no Spirit Vessel.
B35: From Nothing | C35: Jewel | D35: Valor | E35: 0.212 | F35: 0.21 | G35: T15+ (Effigy) | H35: Aloca nós sem conexão: Vile Mending, Grip of Evil, Entropic Incarnation e o cluster de minion perto de Blackflame Covenant. É por isso que esses notables aparecem em 54–67% dos zoos top. | I35: Passives in Radius of (keystone) can be Allocated without being connected to your tree | J35: ≈ 0,21 div · Confira o keystone do raio no anúncio (precisa ser o que alcança os nós de minion).
B36: Flesh Crucible | C36: Jewel | D36: Valor | E36: 0.317 | F36: — | G36: T15+ (Effigy) | H36: Pode rolar Giant's Blood (entre outros keystones) com uma penalidade: alternativa ao Treefingers sem gastar slot de luva. | I36: Concede 1 keystone aleatório (procure Giant's Blood) (10-20)% less de um atributo defensivo/ofensivo | J36: ≈ 0,32 div · Só compre a versão com Giant's Blood e penalidade leve (ex.: less mana).
B37: The Fall of the Axe | C37: Charm | D37: Valor | E37: 0.635 | F37: 0.12 | G37: T15+ (Effigy) | H37: Onslaught quando você é desacelerado: mais velocidade para acompanhar o zoo. | I37: Grants Onslaught during effect | J37: ≈ 0,64 div
B38: Controlled Metamorphosis | C38: Jewel | D38: Luxo | E38: 14.9 | F38: 0.01 | G38: T15+ (Effigy) | H38: Aloca nós do anel médio-grande sem conexão (-5 a -20% resists). O Mattjestic usa para pegar nós de companion longe do caminho. | I38: Only affects Passives in Medium-Large Ring Only affects Passives in Massive Ring Only affects Passives in Medium Ring Only affects Passives in Medium-Small Ring Only affects Passives in Small Ring Only affects Passives in Very Large Ring Only affects Passives in Very Small Ring
B39: Tyranny's Grip | C39: Main-hand | D39: Barato | E39: 0.003 | F39: 0.39 | G39: Arbiter / Min-max | H39: Arma barata popular da Catha's Balance em OUTRAS builds de zoo (spear de 1 mão). NÃO é usada nesta rota: aqui a Chober Chaber faz esse papel e ainda dá +Minion Skills e Spirit. | I39: (150-192)% increased Physical Damage (10-15)% reduced Attack Speed +(15-30) to Strength Strikes deal Splash Damage Knocks Back Enemies on Hit Cannot use Projectile Attacks | J39: Runeforged (nv 38) ≈ 0,003 div · Runemastered (nv 55) ≈ 0,41 div · Só considere se não usar a rota Chober Chaber.
B40: Prism of Belief | C40: Jewel | D40: Valor | E40: 0.003 | F40: 0.08 | G40: Arbiter / Min-max | H40: +1 a +3 níveis em todos os Tamed Companions (Zekoa, beasts). | I40: +(1-3) to Level of all Tamed Companion Skills (versão para a build) | J40: +1 barato · +2/+3 Tamed Companion caro · Procure no trade o mod exato 'Tamed Companion Skills'.
B41: Grip of Kulemak | C41: Anel | D41: Barato | E41: 0.006 | F41: — | G41: Arbiter / Min-max | H41: Citado pelo guia base (Spirit efficiency / vida ao matar / chaos res em aliados, dependendo do roll). | I41: (31-38)% increased Armour (5-9)% increased maximum Mana (15-25)% increased Critical Damage Bonus (37-39)% increased Evasion Rating Hits against you have (20-30)% reduced Critical Damage Bonus (5-9)% increased maximum Life (20-30)% reduced Presence Area of Effect | J41: ≈ 0,006 div
B42: Horror's Flight | C42: Luvas | D42: Valor | E42: 0.104 | F42: 0.03 | G42: Arbiter / Min-max | H42: 200–300% Evasion e attack speed. Com Cadigan's Epiphany vira jewel socket. | I42: (200-300)% increased Evasion Rating (7-17)% increased Attack Speed +(13-23) to Dexterity Adds (19-23) to (31-37) Chaos Damage to Attacks Gain 1 Fear Incarnate when you Cull a target | J42: ≈ 0,10 div
B43: Megalomaniac | C43: Jewel | D43: Valor | E43: 0.317 | F43: 0.07 | G43: Arbiter / Min-max | H43: Aloca notables aleatórios; compre só com notables de minion/defesa. | I43: Aloca notables aleatórios (enchant) | J43: ≈ 0,32 div
B44: Heart of the Well | C44: Jewel | D44: Valor | E44: 0.73 | F44: 0.07 | G44: Arbiter / Min-max | H44: Mods aleatórios; os bons dão resistência física e regeneração para minions. | I44: Gain (9-14)% of Damage as Extra Cold Damage Gain (9-14)% of Damage as Extra Fire Damage Gain (10-15)% of Damage as Extra Lightning Damage (6-12)% increased Critical Damage Bonus (1-2)% increased Movement Speed Minions have (3-12)% additional Physical Damage Reduction (5-9)% chance to Poison on Hit | J44: ≈ 0,73 div
B45: Morior Invictus | C45: Body Armour | D45: Luxo | E45: 6 | F45: 0.11 | G45: Arbiter / Min-max | H45: Por socket preenchido: +8–10% todas as resists, +45–60 vida, +10 Spirit, menos dano crítico recebido. Tanque de verdade para Arbiter. | I45: (300-400)% increased Armour, Evasion and Energy Shield +(5-7) to all Attributes per Socket filled +(45-60) to maximum Life per Socket filled +(50-60) to maximum Mana per Socket filled +(10-13)% to Chaos Resistance per Socket filled (8-11.9) Life Regeneration per second per Socket filled +(8-10)% to all Elemental Resistances per Socket filled | J45: ≈ 6 div · Encha todos os sockets com Idols.
B46: Rite of Passage | C46: Charm | D46: Luxo | E46: 15 | F46: 0.1 | G46: Arbiter / Min-max | H46: Possessão por Azmeri Spirits ao matar raros/únicos. Luxo. | I46: Possessed by Spirit Of The Cat for 13 seconds on use Possessed by Spirit Of The Stag for 15 seconds on use Possessed by Spirit Of The Boar for (10-18) seconds on use Possessed by Spirit Of The Serpent for (10-19) seconds on use Possessed by Spirit Of The Primate for (10-18) seconds on use | J46: ≈ 15 div
B47: Kalandra's Touch | C47: Anel | D47: Luxo | E47: 33 | F47: 0.06 | G47: Arbiter / Min-max | H47: Copia o outro anel (use com um anel rare perfeito). | I47: Reflects opposite Ring | J47: ≈ 33 div
B48: Eshtera's Path | C48: Anel | D48: Luxo | E48: 34 | F48: 0.03 | G48: Arbiter / Min-max | H48: Aceita Sapphire jewel (minion crit/dano) e dá atributos + resists. | I48: You can only Socket Sapphire Jewels in this item (10-20)% increased Rarity of Items found +(10-24) to all Attributes +(5-10)% to Fire and Cold Resistances per Equipped Item with a Lightning Resistance Modifier | J48: ≈ 34 div
B49: Mageblood | C49: Cinto | D49: Luxo | E49: 570 | F49: 0.08 | G49: Arbiter / Min-max | H49: Luxo absoluto: legados de flask permanentes. 13 dos 24 zoos 98+ usam, mas não muda o funcionamento da build. | I49: Legacy of Bismuth Legacy of Granite Legacy of Quicksilver Legacy of Amethyst Legacy of Silver Legacy of Diamond Legacy of Stibnite | J49: ≈ 570 div
A51: IDOLS E SOUL CORES
B52: Idol | C52: Onde | E52: Preço (div) | H52: Efeito
B53: Primate Idol | C53: Sceptre / Capacete | E53: 0.011 | H53: Sceptre: aliados na Presence +40% dano · Capacete: minions +15% vida
B54: Rabbit Idol | C54: Sceptre / Body | E54: 0.094 | H54: Sceptre: +15% Spirit · Bonded: +30% recarga de Command
B55: Idol of Ralakesh | C55: Capacete / Sceptre | E55: 0.056 | H55: Capacete: +8% reservation efficiency de minions · Sceptre bonded: companions +25% vida
B56: Fox Idol | C56: Body / Sceptre | E56: 0.196 | H56: Body: ativa os Bonded dos Idols do item · Sceptre: +50% Presence
B57: Carved Majesty | C57: Body / Luvas / Botas | E57: 85.47 | H57: Body: +3 Spirit por Idol equipado · Luvas: Onslaught nos alvos marcados · bonded: companions +30% dano
B58: Soul Core of Cholotl | C58: Arma / Armadura | H58: Converte 40% dos requisitos em Dexterity (ajuda Chober Chaber)
B59: Greater Rune of Leadership | C59: Arma / Armadura | H59: Arma: minions 10% phys como lightning · bonded: +20% dano de minion

Sheet Passivas & Itens
A1: PASSIVAS & SETS POR FASE — nossa rota
A2: Atos 1–2: leveling de spear. Ato 3+: árvore própria (consenso dos 24 zoos top, sem nós de ataque) e sets com uniques no set principal, barato e completo. Árvore visual no app.
A4: ATO 1 · 18 pontos principais
B5: Notable | C5: Árvore | D5: Novo? | E5: Efeito
B6: Primal Instinct | C6: Principal | D6: NOVO | E6: 8% increased Attack Speed · 6% increased Area of Effect · +10 to Dexterity
B7: Stalk and Leap | C7: Principal | D7: NOVO | E7: 30% increased Melee Damage if you've dealt a Projectile Attack Hit in the past eight seconds · 30% increased Projectile Damage if you've dealt a Melee Hit in the past eight seconds
B8: Disorientation | C8: Principal | D8: NOVO | E8: 25% increased Blind duration · 25% increased Damage with Hits against Blinded Enemies
B9: Set de leveling (spear) | C9: Slot | D9: Único | E9: Mods que importam / sockets / nota
B10: Hunting Spear | C10: Arma (Set 1) | E10: Adds 5 to 9 Physical Damage ; +17 to Accuracy Rating ; +10 to Strength ; Grants 2 Life per Enemy Hit ; 5% increased Light Radius
B11: Leather Buckler | C11: Offhand (Set 1) | E11: —
B12: Surefooted Sigil | C12: Amuleto | D12: Sim | E12: —
B13: Meginord's Girdle | C13: Cinto | D13: Sim | E13: —
B14: Foxshade | C14: Body Armour | D14: Sim | E14: —
B15: Wanderlust | C15: Botas | D15: Sim | E15: —
B16: Ruby Charm | C16: Charm | E16: 16% reduced Charges per use
B17: Topaz Charm | C17: Charm | E17: 18% increased Duration ; 21% Chance to gain a Charge when you kill an enemy
B18: Stocky Mitts | C18: Luvas | E18: Adds 2 to 3 Physical Damage to Attacks ; Adds 1 to 5 Lightning damage to Attacks ; +6 to Strength ; Gain 2 Life per Enemy Hit with Attacks
B19: Goldrim | C19: Capacete | D19: Sim | E19: —
B20: Blackheart | C20: Anel E | D20: Sim | E20: —
B21: Blackheart | C21: Anel D | D21: Sim | E21: —
A23: ATO 2 · 20 pontos principais
B24: Notable | C24: Árvore | D24: Novo? | E24: Efeito
B25: Primal Instinct | C25: Principal | E25: 8% increased Attack Speed · 6% increased Area of Effect · +10 to Dexterity
B26: Stalk and Leap | C26: Principal | E26: 30% increased Melee Damage if you've dealt a Projectile Attack Hit in the past eight seconds · 30% increased Projectile Damage if you've dealt a Melee Hit in the past eight seconds
B27: Disorientation | C27: Principal | E27: 25% increased Blind duration · 25% increased Damage with Hits against Blinded Enemies
B28: Set de leveling (spear) | C28: Slot | D28: Único | E28: Mods que importam / sockets / nota
B29: Skysliver | C29: Arma (Set 1) | D29: Sim | E29: —
B30: Surefooted Sigil | C30: Amuleto | D30: Sim | E30: —
B31: Meginord's Girdle | C31: Cinto | D31: Sim | E31: —
B32: Foxshade | C32: Body Armour | D32: Sim | E32: —
B33: Wanderlust | C33: Botas | D33: Sim | E33: —
B34: Ruby Charm | C34: Charm | E34: 16% reduced Charges per use
B35: Topaz Charm | C35: Charm | E35: 18% increased Duration ; 21% Chance to gain a Charge when you kill an enemy
B36: Runeforged Bound Bracers | C36: Luvas | E36: Adds 1 to 3 Cold damage to Attacks ; +1 to Level of all Melee Skills ; 6% increased Attack Speed ; +7% to Cold Resistance | Sockets/versão: Desert Rune (res. fogo)
B37: Goldrim | C37: Capacete | D37: Sim | E37: —
B38: Blackheart | C38: Anel E | D38: Sim | E38: —
B39: Blackheart | C39: Anel D | D39: Sim | E39: —
A41: ATO 3 · 31 pontos principais · árvore própria (zoos top, sem ataque)
B42: Notable | C42: Árvore | D42: Novo? | E42: Efeito
B43: Blur | C43: Principal | D43: NOVO | E43: 4% increased Movement Speed · 20% increased Evasion Rating · +10 to Dexterity
B44: Catlike Agility | C44: Principal | D44: NOVO | E44: 25% increased Evasion Rating · 40% increased Evasion Rating if you've Dodge Rolled Recently · 3% reduced Movement Speed Penalty from using Skills while moving
B45: Escape Velocity | C45: Principal | D45: NOVO | E45: 3% increased Movement Speed · 30% increased Evasion Rating
B46: Bond of the Mamba | C46: Principal | D46: NOVO | E46: Gain 4% of Physical Damage as extra Chaos Damage · Companions gain 12% Damage as extra Chaos Damage
B47: Trusted Kinship | C47: Principal | D47: NOVO | E47: You can have two Companions of different types · 30% more Reservation Efficiency of Companion Skills · 20% less Reservation Efficiency of non-Companion Skills
B48: Unspoken Bond | C48: Principal | D48: NOVO | E48: Companions have +30% to Chaos Resistance · Companions have +30% to all Elemental Resistances
B49: Bond of the Cat | C49: Principal | D49: NOVO | E49: Companions have 20% increased Movement Speed · 5% reduced Movement Speed Penalty from using Skills while moving
B50: Set principal — BARATO | C50: Slot | D50: Único | E50: Mods que importam / sockets / nota
B51: Rattling Sceptre | C51: Arma (Set 1) | E51: Grants Skill: Skeletal Warrior ; +1/+2 to Level of all Minion Skills ; % increased Spirit | Sockets/versão: Primate Idol (bonus de companion) · sem Idol: Body Rune (vida) | Base rare (não é unique) · qualquer um com +Minion Skills
B52: Trenchtimbre | C52: Offhand (Set 1) | D52: Sim | E52: +1 to Level of all Minion Skills ; (+3 mods de ataque/utilidade que não importam para o zoo) | Sockets/versão: Runa de resistência que faltar (Desert = fogo · Glacial = frio · Storm = raio) | +1 Minion Skills
B53: Capacete rare (Cultist Crown) | C53: Capacete | E53: +1/+2 to Level of all Minion Skills ; +Life ; +Resistências | Sockets/versão: Runa de resistência que faltar (Desert = fogo · Glacial = frio · Storm = raio) · resist no cap: Body Rune (vida)
B54: Foxshade | C54: Body Armour | D54: Sim | E54: +(50-70) to Evasion Rating ; 10% increased Movement Speed when on Full Life ; 100% increased Evasion Rating when on Full Life ; (+1 mod de ataque/utilidade que não importa para o zoo) | Sockets/versão: Runa de resistência que faltar (Desert = fogo · Glacial = frio · Storm = raio) · resist no cap: Body Rune (vida)
B55: Luvas rare | C55: Luvas | E55: +Life ; +Resistências ; +Evasion | Sockets/versão: Runa de resistência que faltar (Desert = fogo · Glacial = frio · Storm = raio) · resist no cap: Body Rune (vida)
B56: Wanderlust | C56: Botas | D56: Sim | E56: 20% increased Movement Speed ; +(10-20) to maximum Energy Shield ; (+2 mods de ataque/utilidade que não importam para o zoo) | Sockets/versão: Runa de resistência que faltar (Desert = fogo · Glacial = frio · Storm = raio) · resist no cap: Body Rune (vida)
B57: Amuleto rare | C57: Amuleto | E57: +1 to Level of all Minion Skills ; +Spirit ; +Life ; +Resistências
B58: Blackheart | C58: Anel E | D58: Sim | E58: (+4 mods de ataque/utilidade que não importam para o zoo)
B59: Blackheart | C59: Anel D | D59: Sim | E59: (+4 mods de ataque/utilidade que não importam para o zoo)
B60: Midnight Braid | C60: Cinto | D60: Sim | E60: +(30-50) to maximum Mana ; +(5-10)% to all Elemental Resistances ; (+1 mod de ataque/utilidade que não importa para o zoo)
B61: Set principal — COMPLETO | C61: Slot | D61: Único | E61: Mods que importam / sockets / nota
B62: Chober Chaber | C62: Arma (Set 1) | D62: Sim | E62: +(80-100) to maximum Mana ; +50 to Spirit ; +2 to Level of all Minion Skills ; Increases and Reductions to Minion Damage also affect you ; (+2 mods de ataque/utilidade que não importam para o zoo) | Sockets/versão: Runeforged, Soul Core de Dexterity (atributos), Soul Core de Dexterity (atributos) | Giant's Blood (Treefingers) + The Vertex para usar com sceptre
B63: Rattling Sceptre | C63: Offhand (Set 1) | E63: Grants Skill: Skeletal Warrior ; +1/+2 to Level of all Minion Skills ; % increased Spirit | Sockets/versão: Primate Idol (bonus de companion) · sem Idol: Body Rune (vida) | Base rare (não é unique) · qualquer um com +Minion Skills
B64: The Vertex | C64: Capacete | D64: Sim | E64: Has no Attribute Requirements ; (100-150)% increased Evasion and Energy Shield ; +(13-17)% to Chaos Resistance ; Equipment has no Attribute Requirements ; Skill Gems have no Attribute Requirements ; (+1 mod de ataque/utilidade que não importa para o zoo) | Sockets/versão: Runa de resistência que faltar (Desert = fogo · Glacial = frio · Storm = raio) · resist no cap: Body Rune (vida) | versão Equipment has no Attribute Requirements
B65: Enfolding Dawn | C65: Body Armour | D65: Sim | E65: (50-100)% increased Armour and Energy Shield ; +100 to Spirit ; +(5-15)% to all Elemental Resistances ; (+1 mod de ataque/utilidade que não importa para o zoo) | Sockets/versão: Runa ancestral (Runeforged), Runa ancestral (Runeforged) | +100 Spirit
B66: Treefingers | C66: Luvas | D66: Sim | E66: +(15-20) to Strength ; Giant's Blood ; (+4 mods de ataque/utilidade que não importam para o zoo) | Sockets/versão: Runa de resistência que faltar (Desert = fogo · Glacial = frio · Storm = raio) · resist no cap: Body Rune (vida) | Giant's Blood
B67: Wanderlust | C67: Botas | D67: Sim | E67: 20% increased Movement Speed ; +(10-20) to maximum Energy Shield ; (+2 mods de ataque/utilidade que não importam para o zoo) | Sockets/versão: Runa de resistência que faltar (Desert = fogo · Glacial = frio · Storm = raio) · resist no cap: Body Rune (vida)
B68: Amuleto rare | C68: Amuleto | E68: +1 to Level of all Minion Skills ; +Spirit ; +Life ; +Resistências
B69: Blackheart | C69: Anel E | D69: Sim | E69: (+4 mods de ataque/utilidade que não importam para o zoo)
B70: Blackheart | C70: Anel D | D70: Sim | E70: (+4 mods de ataque/utilidade que não importam para o zoo)
B71: Midnight Braid | C71: Cinto | D71: Sim | E71: +(30-50) to maximum Mana ; +(5-10)% to all Elemental Resistances ; (+1 mod de ataque/utilidade que não importa para o zoo)
A73: ATO 4 · 51 pontos principais · árvore própria (zoos top, sem ataque)
B74: Notable | C74: Árvore | D74: Novo? | E74: Efeito
B75: Blur | C75: Principal | E75: 4% increased Movement Speed · 20% increased Evasion Rating · +10 to Dexterity
B76: Catlike Agility | C76: Principal | E76: 25% increased Evasion Rating · 40% increased Evasion Rating if you've Dodge Rolled Recently · 3% reduced Movement Speed Penalty from using Skills while moving
B77: Escape Velocity | C77: Principal | E77: 3% increased Movement Speed · 30% increased Evasion Rating
B78: Bond of the Wolf | C78: Principal | D78: NOVO | E78: 6% increased Attack Speed · Companions have 50% chance to gain Onslaught on Kill
B79: Bond of the Mamba | C79: Principal | E79: Gain 4% of Physical Damage as extra Chaos Damage · Companions gain 12% Damage as extra Chaos Damage
B80: Trusted Kinship | C80: Principal | E80: You can have two Companions of different types · 30% more Reservation Efficiency of Companion Skills · 20% less Reservation Efficiency of non-Companion Skills
B81: Inspiring Ally (só passagem) | C81: Principal | D81: NOVO | E81: Increases and Reductions to Companion Damage also apply to you
B82: Easy Going | C82: Principal | D82: NOVO | E82: 25% increased Reservation Efficiency of Companion Skills
B83: Unspoken Bond | C83: Principal | E83: Companions have +30% to Chaos Resistance · Companions have +30% to all Elemental Resistances
B84: Bond of the Cat | C84: Principal | E84: Companions have 20% increased Movement Speed · 5% reduced Movement Speed Penalty from using Skills while moving
B85: Set principal — BARATO | C85: Slot | D85: Único | E85: Mods que importam / sockets / nota
B86: Rattling Sceptre | C86: Arma (Set 1) | E86: Grants Skill: Skeletal Warrior ; +1/+2 to Level of all Minion Skills ; % increased Spirit | Sockets/versão: Primate Idol (bonus de companion) · sem Idol: Body Rune (vida) | Base rare (não é unique) · qualquer um com +Minion Skills
B87: Trenchtimbre | C87: Offhand (Set 1) | D87: Sim | E87: +1 to Level of all Minion Skills ; (+3 mods de ataque/utilidade que não importam para o zoo) | Sockets/versão: Runa de resistência que faltar (Desert = fogo · Glacial = frio · Storm = raio)
B88: Capacete rare (Cultist Crown) | C88: Capacete | E88: +1/+2 to Level of all Minion Skills ; +Life ; +Resistências | Sockets/versão: Runa de resistência que faltar (Desert = fogo · Glacial = frio · Storm = raio) · resist no cap: Body Rune (vida)
B89: Enfolding Dawn | C89: Body Armour | D89: Sim | E89: (50-100)% increased Armour and Energy Shield ; +100 to Spirit ; +(5-15)% to all Elemental Resistances ; (+1 mod de ataque/utilidade que não importa para o zoo) | Sockets/versão: Runa ancestral (Runeforged), Runa ancestral (Runeforged) | +100 Spirit
B90: Luvas rare | C90: Luvas | E90: +Life ; +Resistências ; +Evasion | Sockets/versão: Runa de resistência que faltar (Desert = fogo · Glacial = frio · Storm = raio) · resist no cap: Body Rune (vida)
B91: Bushwhack | C91: Botas | D91: Sim | E91: (15-25)% increased Movement Speed ; (50-80)% increased Evasion Rating ; (+2 mods de ataque/utilidade que não importam para o zoo) | Sockets/versão: Runa de resistência que faltar (Desert = fogo · Glacial = frio · Storm = raio) · resist no cap: Body Rune (vida)
B92: Amuleto rare | C92: Amuleto | E92: +1 to Level of all Minion Skills ; +Spirit ; +Life ; +Resistências
B93: Evergrasping Ring | C93: Anel E | D93: Sim | E93: +(60-100) to maximum Mana ; Allies in your Presence Gain (15-25)% of Damage as Extra Chaos Damage ; Enemies in your Presence Gain (6-12)% of Damage as Extra Chaos Damage
B94: Evergrasping Ring | C94: Anel D | D94: Sim | E94: +(60-100) to maximum Mana ; Allies in your Presence Gain (15-25)% of Damage as Extra Chaos Damage ; Enemies in your Presence Gain (6-12)% of Damage as Extra Chaos Damage
B95: Midnight Braid | C95: Cinto | D95: Sim | E95: +(30-50) to maximum Mana ; +(5-10)% to all Elemental Resistances ; (+1 mod de ataque/utilidade que não importa para o zoo)
B96: Beira's Anguish | C96: Charm | D96: Sim | E96: (20-25)% Chance to gain a Charge when you kill an enemy ; Creates Ignited Ground for 4 seconds when used, Igniting enemies as though dealing Fire damage equal to 500% of your maximum Life
B97: Sanguis Heroum | C97: Charm | D97: Sim | E97: Gains (0.15-0.2) Charges per Second ; Creates Consecrated Ground on use
B98: Set principal — COMPLETO | C98: Slot | D98: Único | E98: Mods que importam / sockets / nota
B99: Chober Chaber | C99: Arma (Set 1) | D99: Sim | E99: +(80-100) to maximum Mana ; +50 to Spirit ; +2 to Level of all Minion Skills ; Increases and Reductions to Minion Damage also affect you ; (+2 mods de ataque/utilidade que não importam para o zoo) | Sockets/versão: Runeforged, Soul Core de Dexterity (atributos), Soul Core de Dexterity (atributos) | Giant's Blood (Treefingers) + The Vertex para usar com sceptre
B100: Rattling Sceptre | C100: Offhand (Set 1) | E100: Grants Skill: Skeletal Warrior ; +1/+2 to Level of all Minion Skills ; % increased Spirit | Sockets/versão: Primate Idol (bonus de companion) · sem Idol: Body Rune (vida) | Base rare (não é unique) · qualquer um com +Minion Skills
B101: The Vertex | C101: Capacete | D101: Sim | E101: Has no Attribute Requirements ; (100-150)% increased Evasion and Energy Shield ; +(13-17)% to Chaos Resistance ; Equipment has no Attribute Requirements ; Skill Gems have no Attribute Requirements ; (+1 mod de ataque/utilidade que não importa para o zoo) | Sockets/versão: Runa de resistência que faltar (Desert = fogo · Glacial = frio · Storm = raio) · resist no cap: Body Rune (vida)
B102: Enfolding Dawn | C102: Body Armour | D102: Sim | E102: (50-100)% increased Armour and Energy Shield ; +100 to Spirit ; +(5-15)% to all Elemental Resistances ; (+1 mod de ataque/utilidade que não importa para o zoo) | Sockets/versão: Runa ancestral (Runeforged), Runa ancestral (Runeforged)
B103: Treefingers | C103: Luvas | D103: Sim | E103: +(15-20) to Strength ; Giant's Blood ; (+4 mods de ataque/utilidade que não importam para o zoo) | Sockets/versão: Runa de resistência que faltar (Desert = fogo · Glacial = frio · Storm = raio) · resist no cap: Body Rune (vida)
B104: Bushwhack | C104: Botas | D104: Sim | E104: (15-25)% increased Movement Speed ; (50-80)% increased Evasion Rating ; (+2 mods de ataque/utilidade que não importam para o zoo) | Sockets/versão: Runa de resistência que faltar (Desert = fogo · Glacial = frio · Storm = raio) · resist no cap: Body Rune (vida)
...

Sheet Fontes
A1: FONTES
A2: Pesquisadas em 15/09/2026. Preços de mercado mudam — por isso usamos faixas (Barato / Valor / Completo).
A3: Fonte | B3: Usado para | C3: Link
A4: Mattjestic — FASTEST 0.5.5 Spirit Walker (26 variantes) | B4: Rota Chober Chaber: gems, supports, itens e árvore por fase | C4: https://mobalytics.gg/poe-2/builds/1-button-crossbow-amazon-mattjestic
A5: Mattjestic — 0.5 Rare Beast Companions Tier-List | B5: Aura bots: custo de Spirit e localização | C5: https://mobalytics.gg/poe-2/profile/mattjestic-multigaming/guides/new-0-4-ultra-rare-beast-companion-farming-guide
A6: imortilize — Zoo Companion Huntress League Starter (v1.1.1, 05/09/2026) | B6: Leveling por ato, gems, quests, ascendência | C6: https://mobalytics.gg/poe-2/builds/companion-huntress-league-starter
A7: imortilize — T15+ Zoo Companion Huntress (0.5.5) | B7: T15 / Arbiter / Uber, gear, beasts, atlas | C7: https://mobalytics.gg/poe-2/builds/zoo-companion-huntress-imortilize
A8: Zizaran — Companion Spirit Walker (Maxroll, 0.5.4) | B8: Tricks de captura, crit Silverfist, idols, auras | C8: https://maxroll.gg/poe2/build-guides/companion-spirit-walker-build-guide
A9: PoE2DB — Spirit Walker | B9: Texto exato dos nós de ascendência | C9: https://poe2db.tw/us/Spirit_Walker
A10: PoE2DB — Darkness Enthroned / Tyranny's Grip / Trenchtimbre / Sylvan's Effigy | B10: Slot e mods dos uniques | C10: https://poe2db.tw/us/Darkness_Enthroned
A11: PoE2DB — Trusted Kinship / Easy Going / Inspiring Ally | B11: Texto dos passivos-chave | C11: https://poe2db.tw/us/Trusted_Kinship
A12: poe.ninja — Spirit Walker Forbidden Rites (builds + economia) | B12: Uso real de uniques, keystones, companions e preços | C12: https://poe.ninja/poe2/builds/forbiddenrites?class=Spirit%20Walker
A13: poe-vault — Spiritwalker Boss Companion Endgame | B13: Zekoa, mods desejados, reroll com Doryani | C13: https://www.poe-vault.com/poe2/huntress/spirit-walker/tamed-boss-beast-build-guide
